mem_to_reg_mux/mem_mux.v
`timescale 1ns/1ps


module mem_mux(clk,mem_to_reg,alu_result,mem_data,pc,out);
input clk;
input [1:0]mem_to_reg;
input [31:0] alu_result;
input [31:0] mem_data;
input [9:0]pc;
output reg [31:0] out;

always @(posedge clk) begin
    if(mem_to_reg==1)
        out=mem_data;
    else if(mem_to_reg==0)
        out=alu_result;
    else if(mem_to_reg==2 || mem_to_reg==3)
        out=pc+4;//pc+4
end


endmodule

data_memory/data_memory.v
`timescale 1ns / 1ps

module data_memory(read_data,size,clk,address,write_data,mem_rd,mem_wr);
input clk;
input size;
input [31:0] address;
input [31:0] write_data;
input mem_rd;
input mem_wr;

reg [7:0] memory[1023:0];// 1023 locations of 4 bytes == 1024 bytes totals.
output reg [31:0] read_data;

always@(posedge clk)begin
	case(size)
	0:begin
	if(mem_rd==1)
		read_data=memory[address];
	if(mem_wr==1)
		memory[address]=write_data;
	end
	1:
	begin
		if(mem_rd==1)
		read_data[7:0]=memory[address];
		read_data[15:8]=memory[address+1];
		read_data[23:16]=memory[address+2];
		read_data[31:024]=memory[address+3];
		if(mem_wr==1)
		memory[address]=write_data[7:0];
		memory[address+1]=write_data[15:8];
		memory[address+2]=write_data[23:16];
		memory[address+3]=write_data[31:24];
	end
	endcase
end

endmodule

ALU/alu.v
`timescale 1ns / 1ps


module alu(clk,a,b,out,alu_control,zero_flag);//s is ALU CONTROL
input clk;
input [31:0] a,b;
input [2:0] alu_control;
output reg zero_flag;
output reg [31:0] out;

always@(*)
begin
	case(alu_control)
	3'b000:
		out=a&b;
	3'b001:
		out=a|b;	
	3'b010:
		out=a+b;
	3'b011:
		out=a-b;
	3'b100:
    begin
        if(a<b)
            out=0;
        else 
            out=1; 
    end
	3'b101:
	 begin
        if(a>=b)
            out=0;
        else 
            out=1; 
    end
	3'b110:
	 begin
        if(a==b)
            out=0;
        else 
            out=1; 
    end
	endcase

    if(out==0)
        zero_flag=1;
    else
        zero_flag=0;
end 
endmodule

alu_src_mux/alu_mux.v
`timescale 1ns/1ps

module alu_mux (clk,alu_src,reg2,imm,out);

input clk;
input alu_src;
input [31:0] reg2;
input [20:0]imm;
output reg [31:0] out;

always @(posedge clk) begin
    if(alu_src==1)
        out=imm;
    else if(alu_src==0)
        out=reg2;
end
    
endmodule

reg_file/reg_file.v
`timescale 1ns / 1ps

module reg_file (
input clk,wr,
input [4:0] r1,r2,rd, //5bit reg address of  the 3 registers for R-type
input [31:0] write_data,// data written into destination register
output reg [31:0] out1,out2// 
);

reg [31:0] registers [31:0];// 32 registers of 32 bit

always@(posedge clk)begin


    if(wr)
        registers[rd]<=write_data;
    else begin
        out1<=registers[r1];
        out2<=registers[r2];
    end
        
end

endmodule

alu_control/alu_control.v
`timescale 1ns / 1ps

module alu_control(clk,func3,func7,opcode,alu_control);
input clk;
input [2:0] func3;
input [6:0] func7;
input [6:0]opcode;
output reg [2:0] alu_control;

parameter r_type=7'b0110011;// add sub etc
parameter s_type=7'b0100011;//sw sb
parameter i_type=7'b0010011;// addi
parameter l_type=7'b0000011;//lw lb
parameter b_type=7'b1100011;//beq bge blt
parameter jal_type=7'b1101111;// jal
parameter jalr_type=7'b1100111;//jalr

always @(posedge clk) begin
    case(opcode)
    r_type:
    begin
        if(func3==3'b111 && func7==7'b0)//and
            alu_control=3'b000;
        else if(func3==3'b110 && func7==7'b0)//or
            alu_control=3'b001;
        else if(func3==3'b0 && func7==7'b0)//add
            alu_control=3'b010;
        else if(func3==3'b0 && func7==7'b0100000)//sub
            alu_control=3'b011;
    end
    s_type:
        alu_control=3'b010;
    i_type:
        alu_control=3'b010;
    l_type:
        alu_control=3'b010;
    b_type:
        begin
            if(func3==3'b100)//blt
                alu_control=3'b100;

            else if(func3==3'b010)//bge
                alu_control=3'b101;
                
            else if(func3==3'b000)//beq
                alu_control=3'b110;
        end
    jal_type:
        alu_control=3'b010;
    jalr_type:
        alu_control=3'b010;
    endcase
end
    
endmodule

control/control.v
`timescale 1ns / 1ps

module control(alu_src,branch,mem_read,mem_to_reg,reg_write,mem_write,alu_op,opcode, clk);
input clk;
input  [6:0] opcode;
output reg alu_src,branch,mem_read,reg_write,mem_write;
output reg [2:0]alu_op;
output reg [1:0]mem_to_reg;// for adding jal and jalr

parameter r_type=7'b0110011;// add sub etc
parameter s_type=7'b0100011;//sw sb
parameter i_type=7'b0010011;// addi
parameter l_type=7'b0000011;//lw lb
parameter b_type=7'b1100011;//beq bge blt
parameter jal_type=7'b1101111;// jal
parameter jalr_type=7'b1100111;//jalr

always@(posedge clk or opcode)begin
	case(opcode)
	r_type:begin
		alu_src=0;
		mem_to_reg=2'b00;
		reg_write=1;
		mem_read=0;
		mem_write=0;
		branch=0;
		alu_op=2'b10;
	end
	s_type:begin
		alu_src=1;
		mem_to_reg=2'bxx;
		reg_write=0;
		mem_read=0;
		mem_write=1;
		branch=0;
		alu_op=2'b00;
	end

    i_type:begin
		alu_src=1;
		mem_to_reg=2'b00;
		reg_write=1;
		mem_read=0;
		mem_write=0;
		branch=0;
		alu_op=2'b00;
	end


	l_type:begin
		alu_src=1;
		mem_to_reg=2'b01;
		reg_write=1;
		mem_read=1;
		mem_write=0;
		branch=0;
		alu_op=2'b00;
	end
	
	b_type:begin
		alu_src=0;
		mem_to_reg=2'bxx;
		reg_write=0;
		mem_read=0;
		mem_write=0;
		branch=1;
		alu_op=2'b01;
	end
    jal_type:
    begin
        alu_src=0;
		mem_to_reg=2'b10;
		reg_write=1;
		mem_read=0;
		mem_write=0;
		branch=1;
		alu_op=2'b11;
    end
    jalr_type:
    begin
        alu_src=1;
		mem_to_reg=2'b11;
		reg_write=1;
		mem_read=0;
		mem_write=0;
		branch=1;
		alu_op=2'b11;
    end

	endcase
end

endmodule

Decoder/decoder.v
`timescale 1ns / 1ps

module decoder(clk,instruction,func3,func7,opcode,r1,r2,rd,imm,size);

input clk;
input [31:0] instruction;// instruction 32 bit
output reg [2:0] func3;//func3 part
output reg [6:0] func7;// func7 part
output reg [6:0] opcode;//opcode part
output reg [4:0] r1,r2,rd;// address of r1,r2,rd
output reg [20:0] imm;//maximum imm can be 20 
output reg size; //size for lw or Lb

parameter r_type=7'b0110011;// add sub etc
parameter s_type=7'b0100011;//sw sb
parameter i_type=7'b0010011;// addi
parameter l_type=7'b0000011;//lw lb
parameter b_type=7'b1100011;//beq bge blt
parameter jal_type=7'b1101111;// jal
parameter jalr_type=7'b1100111;//jalr

always @(posedge clk) begin
    
    func3=0;func7=0;imm=0;r1=0;r2=0;rd=0;// to remove garbage value
    opcode=instruction[6:0];
    size=1;//default size is word 
    case (opcode)
    r_type:
    begin
        rd=instruction[11:7];
        func3=instruction[14:12];
        r1=instruction[19:15];
        r2=instruction[24:20];
        func7=instruction[31:25];
    end
    s_type:
        begin
            imm[4:0]=instruction[11:7];
            func3=instruction[14:12];
            r1=instruction[19:15];
            r2=instruction[24:20];
            imm[11:5]=instruction[31:25];


            if(func3==3'b000)
                size=0;
        end
    i_type:
    begin
        rd=instruction[11:7];
        func3=instruction[14:12];
        r1=instruction[19:15];
        func7=7'bx;
        imm[11:0]=instruction[31:20];
    end
    l_type:
    begin
        rd=instruction[11:7];
        func3=instruction[14:12];
        r1=instruction[19:15];
        func7=7'bx;
        imm[11:0]=instruction[31:20];
        if(func3==3'b000)
                size=0;
    end
    b_type:// shifted right once
    begin
        
        imm[11]=instruction[7];
        imm[4:1]=instruction[11:8];
        func3=instruction[14:12];
        r1=instruction[19:15];
        r2=instruction[24:20];
        imm[10:5]=instruction[30:25];
        imm[12]=instruction[31];

        imm=imm>>>1;//signed right shift
        rd=5'bx;
        func7=7'bx;
    end
    jal_type:begin
        
        rd=instruction[11:7];
        imm[19:12]=instruction[19:12];
        imm[11]=instruction[20];
        imm[10:1]=instruction[30:21];
        imm[20]=instruction[31];

        imm=imm>>>1;//signed right shift
        func3=3'bx;
        r1=5'bx;
        r2=5'bx;
        func7=7'bx;
    end
    jalr_type:
    begin
        rd=instruction[11:7];
        func3=instruction[14:12];
        r1=instruction[19:15];
        func7=7'bx;
        imm[11:0]=instruction[31:20];
    end
    endcase
end
    
endmodule

Instruction_memory/instruction_memory.v
module instruction_memory(clk,read_addr,instruction);
input clk;
input [9:0] read_addr;
output reg [31:0] instruction;
reg [31:0] imemory [1023:0];


always@(posedge clk)
begin
	imemory[0] = 32'b00000000000100010000000010110011; // add x1 x1 x2
	imemory[1] = 32'b00000000000100010000000100110011; // add x2 x1 x2
	imemory[2] = 32'b00000000000100010000000110110011; // add x3 x1 x2
	imemory[3] = 32'b00000000000100010111001000110011; // and x4 x1 x2
	instruction=imemory[read_addr];
end

endmodule

ProgramCounter/ProgramCounter.v
`timescale 1ns / 1ps
//////////////////////////////////////////////////////////////////////////////////
// Company: 
// Engineer: 
// 
// Create Date:    12:32:37 04/10/2023 
// Design Name: 
// Module Name:    ProgramCounter 
// Project Name: 
// Target Devices: 
// Tool versions: 
// Description: 
//
// Dependencies: 
//
// Revision: 
// Revision 0.01 - File Created
// Additional Comments: 
//
//////////////////////////////////////////////////////////////////////////////////
module ProgramCounter(
input clk,reset,
input [20:0]offset,
input branch,
input [31:0]reg_out1,
input [1:0]mem_to_reg,
input zero_flag,
output reg [9:0] count
);


always@(negedge clk)begin
	if(reset)
		count=0;
	else if(branch &&zero_flag && mem_to_reg==2'bx)
		count=count+offset;
	else if(branch && mem_to_reg==2'b11 )
		count=offset+reg_out1;//immediate + register 1
	else if(branch || mem_to_reg==2'b10 )//Btype or jal
		count=count+offset;//pc + immediate
	else
		count=count+1;//pc +4

end

endmodule

Processor/processor.v
`timescale 1ns/1ps

`include "../ALU/alu.v"
`include "../alu_control/alu_control.v"
`include "../alu_src_mux/alu_mux.v"
`include "../control/control.v"
`include "../data_memory/data_memory.v"
`include "../decoder/decoder.v"
`include "../Instruction_memory/instruction_memory.v"
`include "../mem_to_reg_mux/mem_mux.v"
`include "../ProgramCounter/ProgramCounter.v"
`include "../reg_file/reg_file.v"

// module alu(clk,a,b,out,alu_control,zero_flag);//s is ALU CONTROL
// module alu_control(clk,func3,func7,opcode,alu_control);
// module alu_mux (clk,alu_src,reg2,imm,out);
// module control(alu_src,branch,mem_read,mem_to_reg,reg_write,mem_write,alu_op,opcode, clk);
// module data_memory(read_data,clk,address,write_data,mem_rd,mem_wr);
// module decoder(clk,instruction,func3,func7,opcode,r1,r2,rd,imm);
// module instruction_memory(clk,read_addr,instruction);
// module mem_mux(clk,mem_to_reg,alu_result,mem_data,pc,out);
// module ProgramCounter(input clk,reset,input [20:0]offset,input branch,input [31:0]reg_out1,input [1:0]mem_to_reg,output reg [9:0] count
// );
// module reg_file (
// input clk,wr,
// input [4:0] r1,r2,rd, //5bit reg address of  the 3 registers for R-type
// input [31:0] write_data,// data written into destination register
// output reg [31:0] out1,out2// 
// );

module processor(clk,reset,instr,pc_out,imm_out,alu_control);

//inputs
input clk,reset;
output [31:0] instr;
output [9:0]pc_out;

assign instr=instruction;
assign pc_out=pc;
assign imm_out=imm;
assign alu_control=alu_op;

wire [9:0] pc;
ProgramCounter PC1 (clk,reset,imm,branch,out1,mem_to_reg,zero_flag,pc);

// instruction memory output-> decoder input
wire [31:0]instruction;

instruction_memory INSTRUCTION_MEMORY(clk,pc,instruction);

//decoder outputs ->regile,control,alu_control.
wire [2:0]func3;
wire [6:0]func7;
wire [6:0]opcode;
wire [4:0]r1;
wire [4:0]r2;
wire [4:0]rd;
wire [20:0]imm;
wire size;

decoder DECODER (clk,instruction,func3,func7,opcode,r1,r2,rd,imm,size);

//control outputs

wire mem_read;
wire mem_write;
wire alu_src;
wire reg_write;
wire [1:0] mem_to_reg;

control CONTROL (alu_src,branch,mem_read,mem_to_reg,reg_write,mem_write,opcode,clk);

//alu control
wire [2:0]alu_op;
alu_control ALU_C(clk,func3,func7,opcode,alu_op);


//regfile output
wire [31:0] out1;
wire [31:0] out2;

reg_file REG_FILE(clk,reg_write,r1,r2,rd,write_data,out1,out2);


//mux alu src
alu_mux ALU_MUX(clk,alu_src,out2,imm,out2);

//alu outputs
wire zero_flag;
wire [31:0]result;

alu ALU(clk,out1,out2,result,alu_op,zero_flag);

//data memory 
wire [31:0] data_out;
data_memory DATA_MEMORY(data_out,size,clk,result,out2,mem_read,mem_write);
//(read_data,size,clk,address,write_data,mem_rd,mem_wr
//mem to reg mux
wire[31:0]write_data;
mem_mux MEM_MUX(clk,mem_to_reg,result,data_out,pc,write_data);


endmodule

Processor/processor_tb.v
`timescale 1ns/1ps
`include "processor.v"

module processor_tb;

reg clk,reset;
wire [31:0]instr;
wire [9:0] pc_out;

processor uut(clk,reset,instr,pc_out);

always#1clk=~clk;
initial begin
    $dumpfile("proccessor.vcd");
    $dumpvars(0,processor_tb);

    clk=0;reset=1;#2;
    reset=0;
    #20;

    $finish;

end
    
endmodule

Processor/proccessor.vcd
$date
	Sun May 14 19:07:33 2023
$end
$version
	Icarus Verilog
$end
$timescale
	1ps
$end
$scope module processor_tb $end
$var wire 32 ! instr [31:0] $end
$var wire 10 " pc_out [9:0] $end
$var reg 1 # clk $end
$var reg 1 $ reset $end
$scope module uut $end
$var wire 3 % alu_op [2:0] $end
$var wire 1 & alu_src $end
$var wire 1 ' branch $end
$var wire 1 ( clk $end
$var wire 32 ) data_out [31:0] $end
$var wire 3 * func3 [2:0] $end
$var wire 7 + func7 [6:0] $end
$var wire 21 , imm [20:0] $end
$var wire 32 - instr [31:0] $end
$var wire 32 . instruction [31:0] $end
$var wire 1 / mem_read $end
$var wire 2 0 mem_to_reg [1:0] $end
$var wire 1 1 mem_write $end
$var wire 7 2 opcode [6:0] $end
$var wire 32 3 out1 [31:0] $end
$var wire 32 4 out2 [31:0] $end
$var wire 10 5 pc [9:0] $end
$var wire 10 6 pc_out [9:0] $end
$var wire 5 7 r1 [4:0] $end
$var wire 5 8 r2 [4:0] $end
$var wire 5 9 rd [4:0] $end
$var wire 1 : reg_write $end
$var wire 1 ; reset $end
$var wire 32 < result [31:0] $end
$var wire 1 = size $end
$var wire 32 > write_data [31:0] $end
$var wire 1 ? zero_flag $end
$scope module PC1 $end
$var wire 1 ' branch $end
$var wire 1 ( clk $end
$var wire 2 @ mem_to_reg [1:0] $end
$var wire 21 A offset [20:0] $end
$var wire 32 B reg_out1 [31:0] $end
$var wire 1 ; reset $end
$var wire 1 ? zero_flag $end
$var reg 10 C count [9:0] $end
$upscope $end
$scope module INSTRUCTION_MEMORY $end
$var wire 1 ( clk $end
$var wire 10 D read_addr [9:0] $end
$var reg 32 E instruction [31:0] $end
$upscope $end
$scope module DECODER $end
$var wire 1 ( clk $end
$var wire 32 F instruction [31:0] $end
$var reg 3 G func3 [2:0] $end
$var reg 7 H func7 [6:0] $end
$var reg 21 I imm [20:0] $end
$var reg 7 J opcode [6:0] $end
$var reg 5 K r1 [4:0] $end
$var reg 5 L r2 [4:0] $end
$var reg 5 M rd [4:0] $end
$var reg 1 N size $end
$upscope $end
$scope module CONTROL $end
$var wire 1 ( clk $end
$var wire 7 O opcode [6:0] $end
$var reg 3 P alu_op [2:0] $end
$var reg 1 Q alu_src $end
$var reg 1 R branch $end
$var reg 1 S mem_read $end
$var reg 2 T mem_to_reg [1:0] $end
$var reg 1 U mem_write $end
$var reg 1 V reg_write $end
$upscope $end
$scope module ALU_C $end
$var wire 1 ( clk $end
$var wire 3 W func3 [2:0] $end
$var wire 7 X func7 [6:0] $end
$var wire 7 Y opcode [6:0] $end
$var reg 3 Z alu_control [2:0] $end
$upscope $end
$scope module REG_FILE $end
$var wire 1 ( clk $end
$var wire 5 [ r1 [4:0] $end
$var wire 5 \ r2 [4:0] $end
$var wire 5 ] rd [4:0] $end
$var wire 1 : wr $end
$var wire 32 ^ write_data [31:0] $end
$var reg 32 _ out1 [31:0] $end
$var reg 32 ` out2 [31:0] $end
$upscope $end
$scope module ALU_MUX $end
$var wire 1 & alu_src $end
$var wire 1 ( clk $end
$var wire 21 a imm [20:0] $end
$var wire 32 b reg2 [31:0] $end
$var reg 32 c out [31:0] $end
$upscope $end
$scope module ALU $end
$var wire 32 d a [31:0] $end
$var wire 3 e alu_control [2:0] $end
$var wire 32 f b [31:0] $end
$var wire 1 ( clk $end
$var reg 32 g out [31:0] $end
$var reg 1 h zero_flag $end
$upscope $end
$scope module DATA_MEMORY $end
$var wire 32 i address [31:0] $end
$var wire 1 ( clk $end
$var wire 1 / mem_rd $end
$var wire 1 1 mem_wr $end
$var wire 1 = size $end
$var wire 32 j write_data [31:0] $end
$var reg 32 k read_data [31:0] $end
$upscope $end
$scope module MEM_MUX $end
$var wire 32 l alu_result [31:0] $end
$var wire 1 ( clk $end
$var wire 32 m mem_data [31:0] $end
$var wire 2 n mem_to_reg [1:0] $end
$var wire 10 o pc [9:0] $end
$var reg 32 p out [31:0] $end
$upscope $end
$upscope $end
$upscope $end
$enddefinitions $end
#0
$dumpvars
bx p
b0 o
bx n
bx m
bx l
bx k
bx j
bx i
xh
bx g
bx f
bx e
bx d
bx c
bx b
bx a
bx `
bx _
bx ^
bx ]
bx \
bx [
bx Z
bx Y
bx X
bx W
xV
xU
bx T
xS
xR
xQ
bx P
bx O
xN
bx M
bx L
bx K
bx J
bx I
bx H
bx G
bx F
bx E
b0 D
b0 C
bx B
bx A
bx @
x?
bx >
x=
bx <
1;
x:
bx 9
bx 8
bx 7
b0 6
b0 5
bx 4
bx 3
bx 2
x1
bx 0
x/
bx .
bx -
bx ,
bx +
bx *
bx )
0(
x'
x&
bx %
1$
0#
b0 "
bx !
$end
#1000
b100010000000010110011 E
b100010000000010110011 .
b100010000000010110011 F
b100010000000010110011 !
b100010000000010110011 -
1N
1=
b0 M
b0 9
b0 ]
b0 L
b0 8
b0 \
b0 K
b0 7
b0 [
b0 I
b0 ,
b0 A
b0 a
b0 H
b0 +
b0 X
b0 G
b0 *
b0 W
0h
0?
1#
1(
#2000
b1 C
b1 5
b1 D
b1 o
b1 "
b1 6
0#
0(
0$
0;
#3000
b10 P
b10 %
b10 e
0R
0'
0U
01
0S
0/
1V
1:
b0 T
b0 0
b0 @
b0 n
0Q
0&
bx k
b10 Z
b1 L
b1 8
b1 \
b10 K
b10 7
b10 [
b10 M
b10 9
b10 ]
b110011 J
b110011 2
b110011 O
b110011 Y
b100010000000100110011 E
b100010000000100110011 .
b100010000000100110011 F
b100010000000100110011 !
b100010000000100110011 -
1#
1(
#4000
b10 C
b10 5
b10 D
b10 o
b10 "
b10 6
0#
0(
#5000
b100010000000110110011 E
b100010000000110110011 .
b100010000000110110011 F
b100010000000110110011 !
b100010000000110110011 -
b10 M
b10 9
b10 ]
b1 L
b1 8
b1 \
b10 K
b10 7
b10 [
bx k
1#
1(
#6000
b11 C
b11 5
b11 D
b11 o
b11 "
b11 6
0#
0(
#7000
bx k
b0 Z
b0x0 %
b0x0 e
b111 G
b111 *
b111 W
b100 M
b100 9
b100 ]
b1 L
b1 8
b1 \
b10 K
b10 7
b10 [
b100010111001000110011 E
b100010111001000110011 .
b100010111001000110011 F
b100010111001000110011 !
b100010111001000110011 -
1#
1(
#8000
b100 C
b100 5
b100 D
b100 o
b100 "
b100 6
0#
0(
#9000
bx E
bx .
bx F
bx !
bx -
b100 M
b100 9
b100 ]
b1 L
b1 8
b1 \
b10 K
b10 7
b10 [
b111 G
b111 *
b111 W
bx k
1#
1(
#10000
b101 C
b101 5
b101 D
b101 o
b101 "
b101 6
0#
0(
#11000
bx k
bx J
bx 2
bx O
bx Y
b0 M
b0 9
b0 ]
b0 L
b0 8
b0 \
b0 K
b0 7
b0 [
b0 G
b0 *
b0 W
1#
1(
#12000
b110 C
b110 5
b110 D
b110 o
b110 "
b110 6
0#
0(
#13000
bx k
1#
1(
#14000
b111 C
b111 5
b111 D
b111 o
b111 "
b111 6
0#
0(
#15000
bx k
1#
1(
#16000
b1000 C
b1000 5
b1000 D
b1000 o
b1000 "
b1000 6
0#
0(
#17000
bx k
1#
1(
#18000
b1001 C
b1001 5
b1001 D
b1001 o
b1001 "
b1001 6
0#
0(
#19000
bx k
1#
1(
#20000
b1010 C
b1010 5
b1010 D
b1010 o
b1010 "
b1010 6
0#
0(
#21000
bx k
1#
1(
#22000
b1011 C
b1011 5
b1011 D
b1011 o
b1011 "
b1011 6
0#
0(
