mem_to_reg_mux/mem_mux.v
`timescale 1ns/1ps


module mem_mux(clk,mem_to_reg,alu_result,mem_data,pc,out);
input clk;
input [1:0]mem_to_reg;
input [31:0] alu_result;
input [31:0] mem_data;
input [9:0]pc;
output reg [31:0] out;

always @(posedge clk) begin
    if(mem_to_reg==1)
        out=mem_data;
    else if(mem_to_reg==0)
        out=alu_result;
    else if(mem_to_reg==2 || mem_to_reg==3)
        out=pc+4;//pc+4
end


endmodule

data_memory/data_memory.v
`timescale 1ns / 1ps

module data_memory(read_data,size,clk,address,write_data,mem_rd,mem_wr);
input clk;
input size;
input [31:0] address;
input [31:0] write_data;
input mem_rd;
input mem_wr;

reg [7:0] memory[1023:0];// 1023 locations of 4 bytes == 1024 bytes totals.
output reg [31:0] read_data;

always@(posedge clk)begin
	case(size)
	0:begin
	if(mem_rd==1)
		read_data=memory[address];
	if(mem_wr==1)
		memory[address]=write_data;
	end
	1:
	begin
		if(mem_rd==1)
		read_data[7:0]=memory[address];
		read_data[15:8]=memory[address+1];
		read_data[23:16]=memory[address+2];
		read_data[31:024]=memory[address+3];
		if(mem_wr==1)
		memory[address]=write_data[7:0];
		memory[address+1]=write_data[15:8];
		memory[address+2]=write_data[23:16];
		memory[address+3]=write_data[31:24];
	end
	endcase
end

endmodule

ALU/alu.v
`timescale 1ns / 1ps


module alu(clk,a,b,out,alu_control,zero_flag);//s is ALU CONTROL
input clk;
input [31:0] a,b;
input [2:0] alu_control;
output reg zero_flag;
output reg [31:0] out;

always@(*)
begin
	case(alu_control)
	3'b000:
		out=a&b;
	3'b001:
		out=a|b;	
	3'b010:
		out=a+b;
	3'b011:
		out=a-b;
	3'b100:
    begin
        if(a<b)
            out=0;
        else 
            out=1; 
    end
	3'b101:
	 begin
        if(a>=b)
            out=0;
        else 
            out=1; 
    end
	3'b110:
	 begin
        if(a==b)
            out=0;
        else 
            out=1; 
    end
	endcase

    if(out==0)
        zero_flag=1;
    else
        zero_flag=0;
end 
endmodule

alu_src_mux/alu_mux.v
`timescale 1ns/1ps

module alu_mux (clk,alu_src,reg2,imm,out);

input clk;
input alu_src;
input [31:0] reg2;
input [20:0]imm;
output reg [31:0] out;

always @(*) begin
    if(alu_src==1)
        out=imm;
    else if(alu_src==0)
        out=reg2;
end
    
endmodule

reg_file/reg_file.v
`timescale 1ns / 1ps

module reg_file (
input clk,wr,
input [4:0] r1,r2,rd, //5bit reg address of  the 3 registers for R-type
input [31:0] write_data,// data written into destination register
output [31:0] out1,out2// 
);

reg [31:0] registers [31:0];// 32 registers of 32 bit

always@(posedge clk)begin
    registers[0]=0;// register 0 stays 0


    registers[1]=2;
    registers[2]=4;
    registers[3]=5;
    registers[4]=4;
    registers[5]=7;

    if(wr)
        registers[rd]=write_data;
        
end
    assign out1=registers[r1];
    assign out2=registers[r2];

endmodule

alu_control/alu_control.v
`timescale 1ns / 1ps

module alu_control(clk,func3,func7,opcode,alu_control);
input clk;
input [2:0] func3;
input [6:0] func7;
input [6:0]opcode;
output reg [2:0] alu_control;

parameter r_type=7'b0110011;// add sub etc
parameter s_type=7'b0100011;//sw sb
parameter i_type=7'b0010011;// addi
parameter l_type=7'b0000011;//lw lb
parameter b_type=7'b1100011;//beq bge blt
parameter jal_type=7'b1101111;// jal
parameter jalr_type=7'b1100111;//jalr

always @(*) begin
    case(opcode)
    r_type:
    begin
        if(func3==3'b111 && func7==7'b0)//and
            alu_control=3'b000;
        else if(func3==3'b110 && func7==7'b0)//or
            alu_control=3'b001;
        else if(func3==3'b0 && func7==7'b0)//add
            alu_control=3'b010;
        else if(func3==3'b0 && func7==7'b0100000)//sub
            alu_control=3'b011;
    end
    s_type:
        alu_control=3'b010;
    i_type:
        alu_control=3'b010;
    l_type:
        alu_control=3'b010;
    b_type:
        begin
            if(func3==3'b100)//blt
                alu_control=3'b100;

            else if(func3==3'b010)//bge
                alu_control=3'b101;
                
            else if(func3==3'b000)//beq
                alu_control=3'b110;
        end
    jal_type:
        alu_control=3'b010;
    jalr_type:
        alu_control=3'b010;
    endcase
end
    
endmodule

control/control.v
`timescale 1ns / 1ps

module control(alu_src,branch,mem_read,mem_to_reg,reg_write,mem_write,opcode, clk);
input clk;
input  [6:0] opcode;
output reg alu_src,branch,mem_read,reg_write,mem_write;
output reg [1:0]mem_to_reg;// for adding jal and jalr

parameter r_type=7'b0110011;// add sub etc
parameter s_type=7'b0100011;//sw sb
parameter i_type=7'b0010011;// addi
parameter l_type=7'b0000011;//lw lb
parameter b_type=7'b1100011;//beq bge blt
parameter jal_type=7'b1101111;// jal
parameter jalr_type=7'b1100111;//jalr

always@(*)begin
	case(opcode)
	r_type:begin
		alu_src=0;
		mem_to_reg=2'b00;
		reg_write=1;
		mem_read=0;
		mem_write=0;
		branch=0;
	end
	s_type:begin
		alu_src=1;
		mem_to_reg=2'bxx;
		reg_write=0;
		mem_read=0;
		mem_write=1;
		branch=0;
	end

    i_type:begin
		alu_src=1;
		mem_to_reg=2'b00;
		reg_write=1;
		mem_read=0;
		mem_write=0;
		branch=0;
	end


	l_type:begin
		alu_src=1;
		mem_to_reg=2'b01;
		reg_write=1;
		mem_read=1;
		mem_write=0;
		branch=0;
	end
	
	b_type:begin
		alu_src=0;
		mem_to_reg=2'bxx;
		reg_write=0;
		mem_read=0;
		mem_write=0;
		branch=1;
	end
    jal_type:
    begin
        alu_src=0;
		mem_to_reg=2'b10;
		reg_write=1;
		mem_read=0;
		mem_write=0;
		branch=1;
    end
    jalr_type:
    begin
        alu_src=1;
		mem_to_reg=2'b11;
		reg_write=1;
		mem_read=0;
		mem_write=0;
		branch=1;
    end

	endcase
end

endmodule

Decoder/decoder.v
`timescale 1ns / 1ps

module decoder(clk,instruction,func3,func7,opcode,r1,r2,rd,imm,size);

input clk;
input [31:0] instruction;// instruction 32 bit
output reg [2:0] func3;//func3 part
output reg [6:0] func7;// func7 part
output reg [6:0] opcode;//opcode part
output reg [4:0] r1,r2,rd;// address of r1,r2,rd
output reg [20:0] imm;//maximum imm can be 20 
output reg size; //size for lw or Lb

parameter r_type=7'b0110011;// add sub etc
parameter s_type=7'b0100011;//sw sb
parameter i_type=7'b0010011;// addi
parameter l_type=7'b0000011;//lw lb
parameter b_type=7'b1100011;//beq bge blt
parameter jal_type=7'b1101111;// jal
parameter jalr_type=7'b1100111;//jalr

always @(*) begin
    
    func3=3'bx;func7=7'bx;imm=0;r1=5'bx;r2=5'bx;rd=5'bx;// to remove garbage value
    opcode=instruction[6:0];
    size=1;//default size is word 
    case (opcode)
    r_type:
    begin
        rd=instruction[11:7];
        func3=instruction[14:12];
        r1=instruction[19:15];
        r2=instruction[24:20];
        func7=instruction[31:25];
    end
    s_type:
        begin
            imm[4:0]=instruction[11:7];
            func3=instruction[14:12];
            r1=instruction[19:15];
            r2=instruction[24:20];
            imm[11:5]=instruction[31:25];


            if(func3==3'b000)
                size=0;
        end
    i_type:
    begin
        rd=instruction[11:7];
        func3=instruction[14:12];
        r1=instruction[19:15];
        func7=7'bx;
        imm[11:0]=instruction[31:20];
    end
    l_type:
    begin
        rd=instruction[11:7];
        func3=instruction[14:12];
        r1=instruction[19:15];
        func7=7'bx;
        imm[11:0]=instruction[31:20];
        if(func3==3'b000)
                size=0;
    end
    b_type:// shifted right once
    begin
        
        imm[11]=instruction[7];
        imm[4:1]=instruction[11:8];
        func3=instruction[14:12];
        r1=instruction[19:15];
        r2=instruction[24:20];
        imm[10:5]=instruction[30:25];
        imm[12]=instruction[31];

        imm=imm>>>1;//signed right shift
        rd=5'bx;
        func7=7'bx;
    end
    jal_type:begin
        
        rd=instruction[11:7];
        imm[19:12]=instruction[19:12];
        imm[11]=instruction[20];
        imm[10:1]=instruction[30:21];
        imm[20]=instruction[31];

        imm=imm>>>1;//signed right shift
        func3=3'bx;
        r1=5'bx;
        r2=5'bx;
        func7=7'bx;
    end
    jalr_type:
    begin
        rd=instruction[11:7];
        func3=instruction[14:12];
        r1=instruction[19:15];
        func7=7'bx;
        imm[11:0]=instruction[31:20];
    end
    endcase
end
    
endmodule

Instruction_memory/instruction_memory.v
module instruction_memory(clk,read_addr,instruction);
input clk;
input [9:0] read_addr;
output reg [31:0] instruction;
reg [31:0] imemory [1023:0];


always@(*)
begin
	imemory[0] = 32'b00000000001000001000000010110011; // add x1 x1 x2
    imemory[1] = 32'b01000000001100010000000100110011; // sub x2 x2 x3
    imemory[2] = 32'b00000000010100011110000110110011; // or x3 x3 x5
    imemory[3] = 32'b00000000000100100111001000110011; // and x4 x4 x1
    imemory[4] = 32'b00000000010100011000000110000011; // lb x3 5(x5)
    imemory[5] = 32'b00000000010000010000001001100011; // beq x4 x2 1
	instruction=imemory[read_addr];
end

endmodule

ProgramCounter/ProgramCounter.v
`timescale 1ns / 1ps
//////////////////////////////////////////////////////////////////////////////////
// Company: 
// Engineer: 
// 
// Create Date:    12:32:37 04/10/2023 
// Design Name: 
// Module Name:    ProgramCounter 
// Project Name: 
// Target Devices: 
// Tool versions: 
// Description: 
//
// Dependencies: 
//
// Revision: 
// Revision 0.01 - File Created
// Additional Comments: 
//
//////////////////////////////////////////////////////////////////////////////////
module ProgramCounter(
input clk,reset,
input [20:0]offset,
input branch,
input [31:0]reg_out1,
input [1:0]mem_to_reg,
input zero_flag,
output reg [9:0] count
);


always@(posedge clk)begin
	if(reset)
		count=0;
	else if(branch &&zero_flag && mem_to_reg==2'bx)
		count=count+offset;
	else if(branch && mem_to_reg==2'b11 )
		count=offset+reg_out1;//immediate + register 1
	else if(branch || mem_to_reg==2'b10 )//Btype or jal
		count=count+offset;//pc + immediate
	else
		count=count+1;//pc +4

end

endmodule

Processor/processor.v
`timescale 1ns/1ps

`include "../ALU/alu.v"
`include "../alu_control/alu_control.v"
`include "../alu_src_mux/alu_mux.v"
`include "../control/control.v"
`include "../data_memory/data_memory.v"
`include "../decoder/decoder.v"
`include "../Instruction_memory/instruction_memory.v"
`include "../mem_to_reg_mux/mem_mux.v"
`include "../ProgramCounter/ProgramCounter.v"
`include "../reg_file/reg_file.v"

// module alu(clk,a,b,out,alu_control,zero_flag);//s is ALU CONTROL
// module alu_control(clk,func3,func7,opcode,alu_control);
// module alu_mux (clk,alu_src,reg2,imm,out);
// module control(alu_src,branch,mem_read,mem_to_reg,reg_write,mem_write,alu_op,opcode, clk);
// module data_memory(read_data,clk,address,write_data,mem_rd,mem_wr);
// module decoder(clk,instruction,func3,func7,opcode,r1,r2,rd,imm);
// module instruction_memory(clk,read_addr,instruction);
// module mem_mux(clk,mem_to_reg,alu_result,mem_data,pc,out);
// module ProgramCounter(input clk,reset,input [20:0]offset,input branch,input [31:0]reg_out1,input [1:0]mem_to_reg,output reg [9:0] count
// );
// module reg_file (
// input clk,wr,
// input [4:0] r1,r2,rd, //5bit reg address of  the 3 registers for R-type
// input [31:0] write_data,// data written into destination register
// output reg [31:0] out1,out2// 
// );

module processor(clk,reset,instr,pc_out,imm_out,alu_control,reg_out1,reg_out2,alu_result);

//inputs
input clk,reset;
output [31:0] instr;
output [9:0]pc_out;
output [20:0]imm_out;
output [2:0]alu_control;
output [31:0]reg_out1;
output [31:0]reg_out2;
output [31:0]alu_result;

assign instr=instruction;
assign pc_out=pc;
assign imm_out=imm;
assign alu_control=alu_op;
assign reg_out1=out1;
assign reg_out2=out2;
assign alu_result=result;

wire [9:0] pc;
ProgramCounter PC1 (clk,reset,imm,branch,out1,mem_to_reg,zero_flag,pc);

// instruction memory output-> decoder input
wire [31:0]instruction;

instruction_memory INSTRUCTION_MEMORY(clk,pc,instruction);

//decoder outputs ->regile,control,alu_control.
wire [2:0]func3;
wire [6:0]func7;
wire [6:0]opcode;
wire [4:0]r1;
wire [4:0]r2;
wire [4:0]rd;
wire [20:0]imm;
wire size;

decoder DECODER (clk,instruction,func3,func7,opcode,r1,r2,rd,imm,size);

//control outputs

wire mem_read;
wire mem_write;
wire alu_src;
wire reg_write;
wire [1:0] mem_to_reg;

control CONTROL (alu_src,branch,mem_read,mem_to_reg,reg_write,mem_write,opcode,clk);

//alu control
wire [2:0]alu_op;
alu_control ALU_C(clk,func3,func7,opcode,alu_op);


//regfile output
wire [31:0] out1;
wire [31:0] out2;

reg_file REG_FILE(clk,reg_write,r1,r2,rd,write_data,out1,out2);


//mux alu src
wire [31:0]selected;
alu_mux ALU_MUX(clk,alu_src,out2,imm,selected);

//alu outputs
wire zero_flag;
wire [31:0]result;

alu ALU(clk,out1,selected,result,alu_op,zero_flag);

//data memory 
wire [31:0] data_out;
data_memory DATA_MEMORY(data_out,size,clk,result,out2,mem_read,mem_write);
//(read_data,size,clk,address,write_data,mem_rd,mem_wr
//mem to reg mux
wire[31:0]write_data;
mem_mux MEM_MUX(clk,mem_to_reg,result,data_out,pc,write_data);


endmodule

Processor/processor_tb.v
`timescale 1ns/1ps
`include "processor.v"

module processor_tb;

reg clk,reset;
wire [31:0]instr;
wire [9:0] pc_out;
wire [20:0]imm_out;
wire [2:0]alu_control;
wire [31:0]reg_out1;
wire [31:0]reg_out2;
wire [31:0]alu_result;

processor uut(clk,reset,instr,pc_out,imm_out,alu_control,reg_out1,reg_out2,alu_result);

always#1clk=~clk;
initial begin
    $dumpfile("proccessor.vcd");
    $dumpvars(0,processor_tb);

    clk=0;reset=1;#2;
    reset=0;
    #20;

    $finish;

end
    
endmodule

Processor/proccessor.vcd
$date
	Sun May 14 21:01:42 2023
$end
$version
	Icarus Verilog
$end
$timescale
	1ps
$end
$scope module processor_tb $end
$var wire 3 ! alu_control [2:0] $end
$var wire 32 " alu_result [31:0] $end
$var wire 21 # imm_out [20:0] $end
$var wire 32 $ instr [31:0] $end
$var wire 10 % pc_out [9:0] $end
$var wire 32 & reg_out1 [31:0] $end
$var wire 32 ' reg_out2 [31:0] $end
$var reg 1 ( clk $end
$var reg 1 ) reset $end
$scope module uut $end
$var wire 3 * alu_control [2:0] $end
$var wire 3 + alu_op [2:0] $end
$var wire 32 , alu_result [31:0] $end
$var wire 1 - alu_src $end
$var wire 1 . branch $end
$var wire 1 / clk $end
$var wire 32 0 data_out [31:0] $end
$var wire 3 1 func3 [2:0] $end
$var wire 7 2 func7 [6:0] $end
$var wire 21 3 imm [20:0] $end
$var wire 21 4 imm_out [20:0] $end
$var wire 32 5 instr [31:0] $end
$var wire 32 6 instruction [31:0] $end
$var wire 1 7 mem_read $end
$var wire 2 8 mem_to_reg [1:0] $end
$var wire 1 9 mem_write $end
$var wire 7 : opcode [6:0] $end
$var wire 32 ; out1 [31:0] $end
$var wire 32 < out2 [31:0] $end
$var wire 10 = pc [9:0] $end
$var wire 10 > pc_out [9:0] $end
$var wire 5 ? r1 [4:0] $end
$var wire 5 @ r2 [4:0] $end
$var wire 5 A rd [4:0] $end
$var wire 32 B reg_out1 [31:0] $end
$var wire 32 C reg_out2 [31:0] $end
$var wire 1 D reg_write $end
$var wire 1 E reset $end
$var wire 32 F result [31:0] $end
$var wire 32 G selected [31:0] $end
$var wire 1 H size $end
$var wire 32 I write_data [31:0] $end
$var wire 1 J zero_flag $end
$scope module PC1 $end
$var wire 1 . branch $end
$var wire 1 / clk $end
$var wire 2 K mem_to_reg [1:0] $end
$var wire 21 L offset [20:0] $end
$var wire 32 M reg_out1 [31:0] $end
$var wire 1 E reset $end
$var wire 1 J zero_flag $end
$var reg 10 N count [9:0] $end
$upscope $end
$scope module INSTRUCTION_MEMORY $end
$var wire 1 / clk $end
$var wire 10 O read_addr [9:0] $end
$var reg 32 P instruction [31:0] $end
$upscope $end
$scope module DECODER $end
$var wire 1 / clk $end
$var wire 32 Q instruction [31:0] $end
$var reg 3 R func3 [2:0] $end
$var reg 7 S func7 [6:0] $end
$var reg 21 T imm [20:0] $end
$var reg 7 U opcode [6:0] $end
$var reg 5 V r1 [4:0] $end
$var reg 5 W r2 [4:0] $end
$var reg 5 X rd [4:0] $end
$var reg 1 Y size $end
$upscope $end
$scope module CONTROL $end
$var wire 1 / clk $end
$var wire 7 Z opcode [6:0] $end
$var reg 1 [ alu_src $end
$var reg 1 \ branch $end
$var reg 1 ] mem_read $end
$var reg 2 ^ mem_to_reg [1:0] $end
$var reg 1 _ mem_write $end
$var reg 1 ` reg_write $end
$upscope $end
$scope module ALU_C $end
$var wire 1 / clk $end
$var wire 3 a func3 [2:0] $end
$var wire 7 b func7 [6:0] $end
$var wire 7 c opcode [6:0] $end
$var reg 3 d alu_control [2:0] $end
$upscope $end
$scope module REG_FILE $end
$var wire 1 / clk $end
$var wire 32 e out1 [31:0] $end
$var wire 32 f out2 [31:0] $end
$var wire 5 g r1 [4:0] $end
$var wire 5 h r2 [4:0] $end
$var wire 5 i rd [4:0] $end
$var wire 1 D wr $end
$var wire 32 j write_data [31:0] $end
$upscope $end
$scope module ALU_MUX $end
$var wire 1 - alu_src $end
$var wire 1 / clk $end
$var wire 21 k imm [20:0] $end
$var wire 32 l reg2 [31:0] $end
$var reg 32 m out [31:0] $end
$upscope $end
$scope module ALU $end
$var wire 32 n a [31:0] $end
$var wire 3 o alu_control [2:0] $end
$var wire 32 p b [31:0] $end
$var wire 1 / clk $end
$var reg 32 q out [31:0] $end
$var reg 1 r zero_flag $end
$upscope $end
$scope module DATA_MEMORY $end
$var wire 32 s address [31:0] $end
$var wire 1 / clk $end
$var wire 1 7 mem_rd $end
$var wire 1 9 mem_wr $end
$var wire 1 H size $end
$var wire 32 t write_data [31:0] $end
$var reg 32 u read_data [31:0] $end
$upscope $end
$scope module MEM_MUX $end
$var wire 32 v alu_result [31:0] $end
$var wire 1 / clk $end
$var wire 32 w mem_data [31:0] $end
$var wire 2 x mem_to_reg [1:0] $end
$var wire 10 y pc [9:0] $end
$var reg 32 z out [31:0] $end
$upscope $end
$upscope $end
$upscope $end
$enddefinitions $end
#0
$dumpvars
bx z
bx y
bx x
bx w
bx v
bx u
bx t
bx s
xr
bx q
bx p
bx o
bx n
bx m
bx l
bx k
bx j
bx i
bx h
bx g
bx f
bx e
bx d
bx c
bx b
bx a
x`
x_
bx ^
x]
x\
x[
bx Z
xY
bx X
bx W
bx V
bx U
bx T
bx S
bx R
bx Q
bx P
bx O
bx N
bx M
bx L
bx K
xJ
bx I
xH
bx G
bx F
1E
xD
bx C
bx B
bx A
bx @
bx ?
bx >
bx =
bx <
bx ;
bx :
x9
bx 8
x7
bx 6
bx 5
bx 4
bx 3
bx 2
bx 1
bx 0
0/
x.
x-
bx ,
bx +
bx *
1)
0(
bx '
bx &
bx %
bx $
bx #
bx "
bx !
$end
#1000
b110 q
b110 F
b110 s
b110 v
b110 "
b110 ,
b100 m
b100 G
b100 p
0r
0J
b10 d
b10 +
b10 o
b10 !
b10 *
0\
0.
0_
09
0]
07
1`
1D
b0 ^
b0 8
b0 K
b0 x
0[
0-
b0 S
b0 2
b0 b
b10 W
b100 <
b100 f
b100 l
b100 t
b100 '
b100 C
b10 @
b10 h
b1 V
b10 ;
b10 M
b10 e
b10 n
b10 &
b10 B
b1 ?
b1 g
b0 R
b0 1
b0 a
b1 X
b1 A
b1 i
1Y
1H
b110011 U
b110011 :
b110011 Z
b110011 c
b0 T
b0 3
b0 L
b0 k
b0 #
b0 4
b1000001000000010110011 P
b1000001000000010110011 6
b1000001000000010110011 Q
b1000001000000010110011 $
b1000001000000010110011 5
b0 N
b0 =
b0 O
b0 y
b0 %
b0 >
1(
1/
#2000
0(
0/
0)
0E
#3000
b101 m
b101 G
b101 p
b11 d
b11 +
b11 o
b11 !
b11 *
b10 X
b10 A
b10 i
b11 W
b101 <
b101 f
b101 l
b101 t
b101 '
b101 C
b11 @
b11 h
b10 V
b10 ?
b10 g
b100000 S
b100000 2
b100000 b
b0 R
b0 1
b0 a
b11111111111111111111111111111111 q
b11111111111111111111111111111111 F
b11111111111111111111111111111111 s
b11111111111111111111111111111111 v
b11111111111111111111111111111111 "
b11111111111111111111111111111111 ,
b1000000001100010000000100110011 P
b1000000001100010000000100110011 6
b1000000001100010000000100110011 Q
b1000000001100010000000100110011 $
b1000000001100010000000100110011 5
b110 z
b110 I
b110 j
bx u
b100 ;
b100 M
b100 e
b100 n
b100 &
b100 B
b1 N
b1 =
b1 O
b1 y
b1 %
b1 >
1(
1/
#4000
0(
0/
#5000
b111 m
b111 G
b111 p
b1 d
b1 +
b1 o
b1 !
b1 *
b11 X
b11 A
b11 i
b101 W
b111 <
b111 f
b111 l
b111 t
b111 '
b111 C
b101 @
b101 h
b11 V
b11 ?
b11 g
b0 S
b0 2
b0 b
b110 R
b110 1
b110 a
b10100011110000110110011 P
b10100011110000110110011 6
b10100011110000110110011 Q
b10100011110000110110011 $
b10100011110000110110011 5
b111 q
b111 F
b111 s
b111 v
b111 "
b111 ,
b10 N
b10 =
b10 O
b10 y
b10 %
b10 >
b101 ;
b101 M
b101 e
b101 n
b101 &
b101 B
bx u
b11111111111111111111111111111111 z
b11111111111111111111111111111111 I
b11111111111111111111111111111111 j
1(
1/
#6000
0(
0/
#7000
1r
1J
b10 m
b10 G
b10 p
b0 d
b0 +
b0 o
b0 !
b0 *
b100 X
b100 A
b100 i
b1 W
b10 <
b10 f
b10 l
b10 t
b10 '
b10 C
b1 @
b1 h
b100 V
b100 ?
b100 g
b0 S
b0 2
b0 b
b111 R
b111 1
b111 a
b0 q
b0 F
b0 s
b0 v
b0 "
b0 ,
b100100111001000110011 P
b100100111001000110011 6
b100100111001000110011 Q
b100100111001000110011 $
b100100111001000110011 5
b111 z
b111 I
b111 j
bx0000000000000000xxxxxxxx u
bx0000000000000000xxxxxxxx 0
bx0000000000000000xxxxxxxx w
b100 ;
b100 M
b100 e
b100 n
b100 &
b100 B
b11 N
b11 =
b11 O
b11 y
b11 %
b11 >
1(
1/
#8000
0(
0/
#9000
1]
17
b1 ^
b1 8
b1 K
b1 x
1[
1-
b101 m
b101 G
b101 p
0r
0J
b1010 q
b1010 F
b1010 s
b1010 v
b1010 "
b1010 ,
b10 d
b10 +
b10 o
b10 !
b10 *
0Y
0H
b101 T
b101 3
b101 L
b101 k
b101 #
b101 4
b11 U
b11 :
b11 Z
b11 c
b11 X
b11 A
b11 i
bx W
bx <
bx f
bx l
bx t
bx '
bx C
bx @
bx h
b11 V
b11 ?
b11 g
bx S
bx 2
bx b
b0 R
b0 1
b0 a
b10100011000000110000011 P
b10100011000000110000011 6
b10100011000000110000011 Q
b10100011000000110000011 $
b10100011000000110000011 5
b100 N
b100 =
b100 O
b100 y
b100 %
b100 >
b101 ;
b101 M
b101 e
b101 n
b101 &
b101 B
bx0000000000000000xxxxxxxx u
b0 z
b0 I
b0 j
1(
1/
#10000
0(
0/
#11000
1r
1J
1\
1.
0]
07
0`
0D
bx ^
bx 8
bx K
bx x
0[
0-
b100 m
b100 G
b100 p
b110 d
b110 +
b110 o
b110 !
b110 *
b100 W
b100 <
b100 f
b100 l
b100 t
b100 '
b100 C
b100 @
b100 h
1Y
1H
b1100011 U
b1100011 :
b1100011 Z
b1100011 c
bx X
bx A
bx i
b10 V
b10 ?
b10 g
b10 T
b10 3
b10 L
b10 k
b10 #
b10 4
b0 R
b0 1
b0 a
b0 q
b0 F
b0 s
b0 v
b0 "
b0 ,
b10000010000001001100011 P
b10000010000001001100011 6
b10000010000001001100011 Q
b10000010000001001100011 $
b10000010000001001100011 5
b0 u
b0 0
b0 w
b100 ;
b100 M
b100 e
b100 n
b100 &
b100 B
b101 N
b101 =
b101 O
b101 y
b101 %
b101 >
1(
1/
#12000
0(
0/
#13000
0r
0J
b1 q
b1 F
b1 s
b1 v
b1 "
b1 ,
bx m
bx G
bx p
bx U
bx :
bx Z
bx c
bx W
bx <
bx f
bx l
bx t
bx '
bx C
bx @
bx h
bx V
bx ;
bx M
bx e
bx n
bx &
bx B
bx ?
bx g
b0 T
b0 3
b0 L
b0 k
b0 #
b0 4
bx R
bx 1
bx a
bx P
bx 6
bx Q
bx $
bx 5
b111 N
b111 =
b111 O
b111 y
b111 %
b111 >
b0 u
1(
1/
#14000
0(
0/
#15000
bx000000000000000000000000 0
bx000000000000000000000000 w
bx000000000000000000000000 u
1(
1/
#16000
0(
0/
#17000
bx00000000 u
bx00000000 0
bx00000000 w
1(
1/
#18000
0(
0/
#19000
bx00000000 u
1(
1/
#20000
0(
0/
#21000
bx00000000 u
1(
1/
