mem_to_reg_mux/mem_mux.v
`timescale 1ns/1ps


module mem_mux(clk,mem_to_reg,alu_result,mem_data,pc,out);
input clk;
input [1:0]mem_to_reg;
input [31:0] alu_result;
input [31:0] mem_data;
input [9:0]pc;
output reg [31:0] out;

always @(posedge clk) begin
    if(mem_to_reg==1)
        out=mem_data;
    else if(mem_to_reg==0)
        out=alu_result;
    else if(mem_to_reg==2 || mem_to_reg==3)
        out=pc+4;//pc+4
end


endmodule

data_memory/data_memory.v
`timescale 1ns / 1ps

module data_memory(read_data,size,clk,address,write_data,mem_rd,mem_wr);
input clk;
input size;
input [31:0] address;
input [31:0] write_data;
input mem_rd;
input mem_wr;

reg [7:0] memory[1023:0];// 1023 locations of 4 bytes == 1024 bytes totals.
output reg [31:0] read_data;

always@(*)begin


	memory[0]=8'h02;
	memory[1]=8'h02;
	memory[2]=8'h02;
	memory[3]=8'h02;

	memory[4]=9;
	memory[5]=7;
	memory[6]=2;
	memory[7]=6;

	memory[10]=99;

	case(size)
	0:begin
	if(mem_rd==1)
		read_data=memory[address];
	if(mem_wr==1)
		memory[address]=write_data;
	end
	1:
	begin
		if(mem_rd==1)
		begin
		read_data[7:0]=memory[address];
		read_data[15:8]=memory[address+1];
		read_data[23:16]=memory[address+2];
		read_data[31:24]=memory[address+3];
		end
		if(mem_wr==1)
		begin
		memory[address]=write_data[7:0];
		memory[address+1]=write_data[15:8];
		memory[address+2]=write_data[23:16];
		memory[address+3]=write_data[31:24];
		end
	end
	endcase
end

endmodule

ALU/alu.v
`timescale 1ns / 1ps


module alu(clk,a,b,out,alu_control,zero_flag);//s is ALU CONTROL
input clk;
input [31:0] a,b;
input [2:0] alu_control;
output reg zero_flag;
output reg [31:0] out;

always@(*)
begin
	case(alu_control)
	3'b000:
		out=a&b;
	3'b001:
		out=a|b;	
	3'b010:
		out=a+b;
	3'b011:
		out=a-b;
	3'b100:
    begin
        if(a<b)
            out=0;
        else 
            out=1; 
    end
	3'b101:
	 begin
        if(a>=b)
            out=0;
        else 
            out=1; 
    end
	3'b110:
	 begin
        if(a==b)
            out=0;
        else 
            out=1; 
    end
	endcase

    if(out==0)
        zero_flag=1;
    else
        zero_flag=0;
end 
endmodule

alu_src_mux/alu_mux.v
`timescale 1ns/1ps

module alu_mux (clk,alu_src,reg2,imm,out);

input clk;
input alu_src;
input [31:0] reg2;
input [20:0]imm;
output reg [31:0] out;

always @(posedge clk) begin
    if(alu_src==1)
        out=imm;
    else if(alu_src==0)
        out=reg2;
end
    
endmodule

reg_file/reg_file.v
`timescale 1ns / 1ps

module reg_file (
input clk,wr,
input [4:0] r1,r2,rd, //5bit reg address of  the 3 registers for R-type
input [31:0] write_data,// data written into destination register
output reg [31:0] out1,out2// 
);

reg [31:0] registers [31:0];// 32 registers of 32 bit

always@(posedge clk)begin


    if(wr)
        registers[rd]<=write_data;
    else begin
        out1<=registers[r1];
        out2<=registers[r2];
    end
        
end

endmodule

alu_control/alu_control.v
`timescale 1ns / 1ps

module alu_control(clk,func3,func7,opcode,alu_control);
input clk;
input [2:0] func3;
input [6:0] func7;
input [6:0]opcode;
output reg [2:0] alu_control;

parameter r_type=7'b0110011;// add sub etc
parameter s_type=7'b0100011;//sw sb
parameter i_type=7'b0010011;// addi
parameter l_type=7'b0000011;//lw lb
parameter b_type=7'b1100011;//beq bge blt
parameter jal_type=7'b1101111;// jal
parameter jalr_type=7'b1100111;//jalr

always @(posedge clk) begin
    case(opcode)
    r_type:
    begin
        if(func3==3'b111 && func7==7'b0)//and
            alu_control=3'b000;
        else if(func3==3'b110 && func7==7'b0)//or
            alu_control=3'b001;
        else if(func3==3'b0 && func7==7'b0)//add
            alu_control=3'b010;
        else if(func3==3'b0 && func7==7'b0100000)//sub
            alu_control=3'b011;
    end
    s_type:
        alu_control=3'b010;
    i_type:
        alu_control=3'b010;
    l_type:
        alu_control=3'b010;
    b_type:
        begin
            if(func3==3'b100)//blt
                alu_control=3'b100;

            else if(func3==3'b010)//bge
                alu_control=3'b101;
                
            else if(func3==3'b000)//beq
                alu_control=3'b110;
        end
    jal_type:
        alu_control=3'b010;
    jalr_type:
        alu_control=3'b010;
    endcase
end
    
endmodule

control/control.v
`timescale 1ns / 1ps

module control(alu_src,branch,mem_read,mem_to_reg,reg_write,mem_write,opcode, clk);
input clk;
input  [6:0] opcode;
output reg alu_src,branch,mem_read,reg_write,mem_write;
output reg [1:0]mem_to_reg;// for adding jal and jalr

parameter r_type=7'b0110011;// add sub etc
parameter s_type=7'b0100011;//sw sb
parameter i_type=7'b0010011;// addi
parameter l_type=7'b0000011;//lw lb
parameter b_type=7'b1100011;//beq bge blt
parameter jal_type=7'b1101111;// jal
parameter jalr_type=7'b1100111;//jalr

always@(*)begin
	case(opcode)
	r_type:begin
		alu_src=0;
		mem_to_reg=2'b00;
		reg_write=1;
		mem_read=0;
		mem_write=0;
		branch=0;
	end
	s_type:begin
		alu_src=1;
		mem_to_reg=2'bxx;
		reg_write=0;
		mem_read=0;
		mem_write=1;
		branch=0;
	end

    i_type:begin
		alu_src=1;
		mem_to_reg=2'b00;
		reg_write=1;
		mem_read=0;
		mem_write=0;
		branch=0;
	end


	l_type:begin
		alu_src=1;
		mem_to_reg=2'b01;
		reg_write=1;
		mem_read=1;
		mem_write=0;
		branch=0;
	end
	
	b_type:begin
		alu_src=0;
		mem_to_reg=2'bx;
		reg_write=0;
		mem_read=0;
		mem_write=0;
		branch=1;
	end
    jal_type:
    begin
        alu_src=0;
		mem_to_reg=2'b10;
		reg_write=1;
		mem_read=0;
		mem_write=0;
		branch=1;
    end
    jalr_type:
    begin
        alu_src=1;
		mem_to_reg=2'b11;
		reg_write=1;
		mem_read=0;
		mem_write=0;
		branch=1;
    end

	endcase
end

endmodule

Decoder/decoder.v
`timescale 1ns / 1ps

module decoder(clk,instruction,func3,func7,opcode,r1,r2,rd,imm,size);

input clk;
input [31:0] instruction;// instruction 32 bit
output reg [2:0] func3;//func3 part
output reg [6:0] func7;// func7 part
output reg [6:0] opcode;//opcode part
output reg [4:0] r1,r2,rd;// address of r1,r2,rd
output reg [20:0] imm;//maximum imm can be 20 
output reg size; //size for lw or Lb

parameter r_type=7'b0110011;// add sub etc
parameter s_type=7'b0100011;//sw sb
parameter i_type=7'b0010011;// addi
parameter l_type=7'b0000011;//lw lb
parameter b_type=7'b1100011;//beq bge blt
parameter jal_type=7'b1101111;// jal
parameter jalr_type=7'b1100111;//jalr

always @(posedge clk) begin
    
    func3=0;func7=0;imm=0;r1=0;r2=0;rd=0;// to remove garbage value
    opcode=instruction[6:0];
    size=1;//default size is word 
    case (opcode)
    r_type:
    begin
        rd=instruction[11:7];
        func3=instruction[14:12];
        r1=instruction[19:15];
        r2=instruction[24:20];
        func7=instruction[31:25];
    end
    s_type:
        begin
            imm[4:0]=instruction[11:7];
            func3=instruction[14:12];
            r1=instruction[19:15];
            r2=instruction[24:20];
            imm[11:5]=instruction[31:25];


            if(func3==3'b000)
                size=0;
        end
    i_type:
    begin
        rd=instruction[11:7];
        func3=instruction[14:12];
        r1=instruction[19:15];
        func7=7'bx;
        imm[11:0]=instruction[31:20];
    end
    l_type:
    begin
        rd=instruction[11:7];
        func3=instruction[14:12];
        r1=instruction[19:15];
        func7=7'bx;
        imm[11:0]=instruction[31:20];
        if(func3==3'b000)
                size=0;
    end
    b_type:// shifted right once
    begin
        
        imm[11]=instruction[7];
        imm[4:1]=instruction[11:8];
        func3=instruction[14:12];
        r1=instruction[19:15];
        r2=instruction[24:20];
        imm[10:5]=instruction[30:25];
        imm[12]=instruction[31];

        imm=imm>>>1;//signed right shift
        rd=5'bx;
        func7=7'bx;
    end
    jal_type:begin
        
        rd=instruction[11:7];
        imm[19:12]=instruction[19:12];
        imm[11]=instruction[20];
        imm[10:1]=instruction[30:21];
        imm[20]=instruction[31];

        imm=imm>>>1;//signed right shift
        func3=3'bx;
        r1=5'bx;
        r2=5'bx;
        func7=7'bx;
    end
    jalr_type:
    begin
        rd=instruction[11:7];
        func3=instruction[14:12];
        r1=instruction[19:15];
        func7=7'bx;
        imm[11:0]=instruction[31:20];
    end
    endcase
end
    
endmodule

Instruction_memory/instruction_memory.v
module instruction_memory(clk,read_addr,instruction);
input clk;
input [9:0] read_addr;
output reg [31:0] instruction;
reg [31:0] imemory [1023:0];


always@(*)
begin
	//fill with instructions
    imemory[0] = 32'b00000000001000001000000010110011;   // add x1 x1 x2
    imemory[1] = 32'b01000000001100010000000100110011;   // sub x2 x2 x3
    imemory[2] = 32'b00000000000100100111001000110011;   // and x4 x4 x1
    imemory[3] = 32'b00000000010100011110000110110011;   // or x3 x3 x5
    imemory[4] = 32'b00000000110000010000001000010011;   // addi x4 x2 12
    imemory[5] = 32'b00000001011100000010000110000011;   // lw x3 23(x0)
    imemory[6] = 32'b00000000010100011000000110000011;   // lb x5 5(x3)
    imemory[7] = 32'b00000000010100011010001010100011;   // sw x5 5(x3)
    imemory[8] = 32'b00000000001000001000110100100011;   // sb x6 90(x1)
    imemory[9] = 32'b00000001000000010000001001100011;   // beq x4 x2 4
	instruction=imemory[read_addr];
end

endmodule

ProgramCounter/ProgramCounter.v
`timescale 1ns / 1ps
//////////////////////////////////////////////////////////////////////////////////
// Company: 
// Engineer: 
// 
// Create Date:    12:32:37 04/10/2023 
// Design Name: 
// Module Name:    ProgramCounter 
// Project Name: 
// Target Devices: 
// Tool versions: 
// Description: 
//
// Dependencies: 
//
// Revision: 
// Revision 0.01 - File Created
// Additional Comments: 
//
//////////////////////////////////////////////////////////////////////////////////
module ProgramCounter(
input clk,reset,
input [20:0]offset,
input branch,
input [31:0]reg_out1,
input [1:0]mem_to_reg,
input zero_flag;
output reg [9:0] count
);


always@(posedge clk)begin
	if(reset)
		count=0;
	else if(branch &&zero_flag && mem_to_reg==2'bx)
		count=count+offset;
	else if(branch && mem_to_reg==2'b11 )
		count=offset+reg_out1;//immediate + register 1
	else if(branch || mem_to_reg==2'b10 )//Btype or jal
		count=count+offset;//pc + immediate
	else
		count=count+4;//pc +4

end

endmodule

Processor/processor.v
`timescale 1ns/1ps

`include "../ALU/alu.v"
`include "../alu_control/alu_control.v"
`include "../alu_src_mux/alu_mux.v"
`include "../control/control.v"
`include "../data_memory/data_memory.v"
`include "../decoder/decoder.v"
`include "../Instruction_memory/instruction_memory.v"
`include "../mem_to_reg_mux/mem_mux.v"
`include "../ProgramCounter/ProgramCounter.v"
`include "../reg_file/reg_file.v"

// module alu(clk,a,b,out,alu_control,zero_flag);//s is ALU CONTROL
// module alu_control(clk,func3,func7,opcode,alu_control);
// module alu_mux (clk,alu_src,reg2,imm,out);
// module control(alu_src,branch,mem_read,mem_to_reg,reg_write,mem_write,alu_op,opcode, clk);
// module data_memory(read_data,clk,address,write_data,mem_rd,mem_wr);
// module decoder(clk,instruction,func3,func7,opcode,r1,r2,rd,imm);
// module instruction_memory(clk,read_addr,instruction);
// module mem_mux(clk,mem_to_reg,alu_result,mem_data,pc,out);
// module ProgramCounter(input clk,reset,input [20:0]offset,input branch,input [31:0]reg_out1,input [1:0]mem_to_reg,output reg [9:0] count
// );
// module reg_file (
// input clk,wr,
// input [4:0] r1,r2,rd, //5bit reg address of  the 3 registers for R-type
// input [31:0] write_data,// data written into destination register
// output reg [31:0] out1,out2// 
// );

module processor(clk,reset,instr,pc_out,imm_out,alu_control,reg_out1,reg_out2,alu_result,flag,read_data);

//inputs
input clk,reset;
output [31:0] instr;
output [9:0]pc_out;
output [20:0]imm_out;
output [2:0]alu_control;
output [31:0]reg_out1;
output [31:0]reg_out2;
output [31:0]alu_result;
output flag;
output [31:0]read_data;

assign instr=instruction;
assign pc_out=pc;
assign imm_out=imm;
assign alu_control=alu_op;
assign reg_out1=out1;
assign reg_out2=out2;
assign alu_result=result;
assign read_data=data_out;
assign flag=zero_flag;

wire [9:0] pc;
ProgramCounter PC1 (clk,reset,imm,branch,out1,mem_to_reg,zero_flag,pc);

// instruction memory output-> decoder input
wire [31:0]instruction;

instruction_memory INSTRUCTION_MEMORY(clk,pc,instruction);

//decoder outputs ->regile,control,alu_control.
wire [2:0]func3;
wire [6:0]func7;
wire [6:0]opcode;
wire [4:0]r1;
wire [4:0]r2;
wire [4:0]rd;
wire [20:0]imm;
wire size;

decoder DECODER (clk,instruction,func3,func7,opcode,r1,r2,rd,imm,size);

//control outputs

wire mem_read;
wire mem_write;
wire alu_src;
wire reg_write;
wire [1:0] mem_to_reg;

control CONTROL (alu_src,branch,mem_read,mem_to_reg,reg_write,mem_write,opcode,clk);

//alu control
wire [2:0]alu_op;
alu_control ALU_C(clk,func3,func7,opcode,alu_op);


//regfile output
wire [31:0] out1;
wire [31:0] out2;

reg_file REG_FILE(clk,reg_write,r1,r2,rd,write_data,out1,out2);


//mux alu src
wire [31:0]selected;
alu_mux ALU_MUX(clk,alu_src,out2,imm,selected);

//alu outputs
wire zero_flag;
wire [31:0]result;

alu ALU(clk,out1,selected,result,alu_op,zero_flag);

//data memory 
wire [31:0] data_out;
data_memory DATA_MEMORY(data_out,size,clk,result,out2,mem_read,mem_write);

//mem to reg mux
wire[31:0]write_data;
mem_mux MEM_MUX(clk,mem_to_reg,result,data_out,pc,write_data);


endmodule

Processor/processor_tb.v
`timescale 1ns/1ps
`include "processor.v"

module processor_tb;

reg clk,reset;
wire [31:0]instr;
wire [9:0] pc_out;
wire [20:0]imm_out;
wire [2:0]alu_control;
wire [31:0]reg_out1;
wire [31:0]reg_out2;
wire [31:0]alu_result;
wire flag;
wire [31:0]read_data;

processor uut(clk,reset,instr,pc_out,imm_out,alu_control,reg_out1,reg_out2,alu_result,flag,read_data);

always#1clk=~clk;
initial begin
    $dumpfile("proccessor.vcd");
    $dumpvars(0,processor_tb);

    clk=0;reset=1;#2;
    reset=0;
    #20;

    $finish;

end
    
endmodule

Processor/proccessor.vcd
$date
	Sun May 14 22:02:18 2023
$end
$version
	Icarus Verilog
$end
$timescale
	1ps
$end
$scope module processor_tb $end
$var wire 3 ! alu_control [2:0] $end
$var wire 32 " alu_result [31:0] $end
$var wire 1 # flag $end
$var wire 21 $ imm_out [20:0] $end
$var wire 32 % instr [31:0] $end
$var wire 10 & pc_out [9:0] $end
$var wire 32 ' read_data [31:0] $end
$var wire 32 ( reg_out1 [31:0] $end
$var wire 32 ) reg_out2 [31:0] $end
$var reg 1 * clk $end
$var reg 1 + reset $end
$scope module uut $end
$var wire 3 , alu_control [2:0] $end
$var wire 3 - alu_op [2:0] $end
$var wire 32 . alu_result [31:0] $end
$var wire 1 / alu_src $end
$var wire 1 0 branch $end
$var wire 1 1 clk $end
$var wire 32 2 data_out [31:0] $end
$var wire 1 # flag $end
$var wire 3 3 func3 [2:0] $end
$var wire 7 4 func7 [6:0] $end
$var wire 21 5 imm [20:0] $end
$var wire 21 6 imm_out [20:0] $end
$var wire 32 7 instr [31:0] $end
$var wire 32 8 instruction [31:0] $end
$var wire 1 9 mem_read $end
$var wire 2 : mem_to_reg [1:0] $end
$var wire 1 ; mem_write $end
$var wire 7 < opcode [6:0] $end
$var wire 32 = out1 [31:0] $end
$var wire 32 > out2 [31:0] $end
$var wire 10 ? pc [9:0] $end
$var wire 10 @ pc_out [9:0] $end
$var wire 5 A r1 [4:0] $end
$var wire 5 B r2 [4:0] $end
$var wire 5 C rd [4:0] $end
$var wire 32 D read_data [31:0] $end
$var wire 32 E reg_out1 [31:0] $end
$var wire 32 F reg_out2 [31:0] $end
$var wire 1 G reg_write $end
$var wire 1 H reset $end
$var wire 32 I result [31:0] $end
$var wire 32 J selected [31:0] $end
$var wire 1 K size $end
$var wire 32 L write_data [31:0] $end
$var wire 1 M zero_flag $end
$scope module PC1 $end
$var wire 1 0 branch $end
$var wire 1 1 clk $end
$var wire 2 N mem_to_reg [1:0] $end
$var wire 21 O offset [20:0] $end
$var wire 32 P reg_out1 [31:0] $end
$var wire 1 H reset $end
$var wire 1 M zero_flag $end
$var reg 10 Q count [9:0] $end
$upscope $end
$scope module INSTRUCTION_MEMORY $end
$var wire 1 1 clk $end
$var wire 10 R read_addr [9:0] $end
$var reg 32 S instruction [31:0] $end
$upscope $end
$scope module DECODER $end
$var wire 1 1 clk $end
$var wire 32 T instruction [31:0] $end
$var reg 3 U func3 [2:0] $end
$var reg 7 V func7 [6:0] $end
$var reg 21 W imm [20:0] $end
$var reg 7 X opcode [6:0] $end
$var reg 5 Y r1 [4:0] $end
$var reg 5 Z r2 [4:0] $end
$var reg 5 [ rd [4:0] $end
$var reg 1 \ size $end
$upscope $end
$scope module CONTROL $end
$var wire 1 1 clk $end
$var wire 7 ] opcode [6:0] $end
$var reg 1 ^ alu_src $end
$var reg 1 _ branch $end
$var reg 1 ` mem_read $end
$var reg 2 a mem_to_reg [1:0] $end
$var reg 1 b mem_write $end
$var reg 1 c reg_write $end
$upscope $end
$scope module ALU_C $end
$var wire 1 1 clk $end
$var wire 3 d func3 [2:0] $end
$var wire 7 e func7 [6:0] $end
$var wire 7 f opcode [6:0] $end
$var reg 3 g alu_control [2:0] $end
$upscope $end
$scope module REG_FILE $end
$var wire 1 1 clk $end
$var wire 32 h out1 [31:0] $end
$var wire 32 i out2 [31:0] $end
$var wire 5 j r1 [4:0] $end
$var wire 5 k r2 [4:0] $end
$var wire 5 l rd [4:0] $end
$var wire 1 G wr $end
$var wire 32 m write_data [31:0] $end
$upscope $end
$scope module ALU_MUX $end
$var wire 1 / alu_src $end
$var wire 1 1 clk $end
$var wire 21 n imm [20:0] $end
$var wire 32 o reg2 [31:0] $end
$var reg 32 p out [31:0] $end
$upscope $end
$scope module ALU $end
$var wire 32 q a [31:0] $end
$var wire 3 r alu_control [2:0] $end
$var wire 32 s b [31:0] $end
$var wire 1 1 clk $end
$var reg 32 t out [31:0] $end
$var reg 1 u zero_flag $end
$upscope $end
$scope module DATA_MEMORY $end
$var wire 32 v address [31:0] $end
$var wire 1 1 clk $end
$var wire 1 9 mem_rd $end
$var wire 1 ; mem_wr $end
$var wire 1 K size $end
$var wire 32 w write_data [31:0] $end
$var reg 32 x read_data [31:0] $end
$upscope $end
$scope module MEM_MUX $end
$var wire 32 y alu_result [31:0] $end
$var wire 1 1 clk $end
$var wire 32 z mem_data [31:0] $end
$var wire 2 { mem_to_reg [1:0] $end
$var wire 10 | pc [9:0] $end
$var reg 32 } out [31:0] $end
$upscope $end
$upscope $end
$upscope $end
$enddefinitions $end
#0
$dumpvars
bx }
bx |
bx {
bx z
bx y
bx x
bx w
bx v
xu
bx t
bx s
bx r
bx q
bx p
bx o
bx n
bx m
bx l
bx k
bx j
bx i
bx h
bx g
bx f
bx e
bx d
xc
xb
bx a
x`
x_
x^
bx ]
x\
bx [
bx Z
bx Y
bx X
bx W
bx V
bx U
bx T
bx S
bx R
bx Q
bx P
bx O
bx N
xM
bx L
xK
bx J
bx I
1H
xG
bx F
bx E
bx D
bx C
bx B
bx A
bx @
bx ?
bx >
bx =
bx <
x;
bx :
x9
bx 8
bx 7
bx 6
bx 5
bx 4
bx 3
bx 2
01
x0
x/
bx .
bx -
bx ,
1+
0*
bx )
bx (
bx '
bx &
bx %
bx $
x#
bx "
bx !
$end
#1000
b110 t
b110 I
b110 v
b110 y
b110 "
b110 .
b100 p
b100 J
b100 s
0u
0M
0#
b10 g
b10 -
b10 r
b10 !
b10 ,
0_
00
0b
0;
0`
09
1c
1G
b0 a
b0 :
b0 N
b0 {
0^
0/
b0 V
b0 4
b0 e
b10 Z
b100 >
b100 i
b100 o
b100 w
b100 )
b100 F
b10 B
b10 k
b1 Y
b10 =
b10 P
b10 h
b10 q
b10 (
b10 E
b1 A
b1 j
b0 U
b0 3
b0 d
b1 [
b1 C
b1 l
1\
1K
b110011 X
b110011 <
b110011 ]
b110011 f
b0 W
b0 5
b0 O
b0 n
b0 $
b0 6
b1000001000000010110011 S
b1000001000000010110011 8
b1000001000000010110011 T
b1000001000000010110011 %
b1000001000000010110011 7
b0 Q
b0 ?
b0 R
b0 |
b0 &
b0 @
1*
11
#2000
0*
01
0+
0H
#3000
b101 p
b101 J
b101 s
b11 g
b11 -
b11 r
b11 !
b11 ,
b10 [
b10 C
b10 l
b11 Z
b101 >
b101 i
b101 o
b101 w
b101 )
b101 F
b11 B
b11 k
b10 Y
b10 A
b10 j
b100000 V
b100000 4
b100000 e
b0 U
b0 3
b0 d
b11111111111111111111111111111111 t
b11111111111111111111111111111111 I
b11111111111111111111111111111111 v
b11111111111111111111111111111111 y
b11111111111111111111111111111111 "
b11111111111111111111111111111111 .
b1000000001100010000000100110011 S
b1000000001100010000000100110011 8
b1000000001100010000000100110011 T
b1000000001100010000000100110011 %
b1000000001100010000000100110011 7
b110 }
b110 L
b110 m
b100 =
b100 P
b100 h
b100 q
b100 (
b100 E
b1 Q
b1 ?
b1 R
b1 |
b1 &
b1 @
1*
11
#4000
0*
01
#5000
1u
1M
1#
b10 p
b10 J
b10 s
b0 g
b0 -
b0 r
b0 !
b0 ,
b100 [
b100 C
b100 l
b1 Z
b10 >
b10 i
b10 o
b10 w
b10 )
b10 F
b1 B
b1 k
b100 Y
b100 A
b100 j
b0 V
b0 4
b0 e
b111 U
b111 3
b111 d
b100100111001000110011 S
b100100111001000110011 8
b100100111001000110011 T
b100100111001000110011 %
b100100111001000110011 7
b0 t
b0 I
b0 v
b0 y
b0 "
b0 .
b10 Q
b10 ?
b10 R
b10 |
b10 &
b10 @
b100 =
b100 P
b100 h
b100 q
b100 (
b100 E
b11111111111111111111111111111111 }
b11111111111111111111111111111111 L
b11111111111111111111111111111111 m
1*
11
#6000
0*
01
#7000
b111 p
b111 J
b111 s
b1 g
b1 -
b1 r
b1 !
b1 ,
b11 [
b11 C
b11 l
b101 Z
b111 >
b111 i
b111 o
b111 w
b111 )
b111 F
b101 B
b101 k
b11 Y
b11 A
b11 j
b0 V
b0 4
b0 e
b110 U
b110 3
b110 d
0u
0M
0#
b111 t
b111 I
b111 v
b111 y
b111 "
b111 .
b10100011110000110110011 S
b10100011110000110110011 8
b10100011110000110110011 T
b10100011110000110110011 %
b10100011110000110110011 7
b0 }
b0 L
b0 m
b101 =
b101 P
b101 h
b101 q
b101 (
b101 E
b11 Q
b11 ?
b11 R
b11 |
b11 &
b11 @
1*
11
#8000
0*
01
#9000
1^
1/
b1100 p
b1100 J
b1100 s
b10000 t
b10000 I
b10000 v
b10000 y
b10000 "
b10000 .
b10 g
b10 -
b10 r
b10 !
b10 ,
b1100 W
b1100 5
b1100 O
b1100 n
b1100 $
b1100 6
b10011 X
b10011 <
b10011 ]
b10011 f
b100 [
b100 C
b100 l
bx Z
bx >
bx i
bx o
bx w
bx )
bx F
bx B
bx k
b10 Y
b10 A
b10 j
bx V
bx 4
bx e
b0 U
b0 3
b0 d
b110000010000001000010011 S
b110000010000001000010011 8
b110000010000001000010011 T
b110000010000001000010011 %
b110000010000001000010011 7
b100 Q
b100 ?
b100 R
b100 |
b100 &
b100 @
b100 =
b100 P
b100 h
b100 q
b100 (
b100 E
b111 }
b111 L
b111 m
1*
11
#10000
0*
01
#11000
bx x
1`
19
b1 a
b1 :
b1 N
b1 {
b10111 t
b10111 I
b10111 v
b10111 y
b10111 "
b10111 .
b10111 p
b10111 J
b10111 s
b11 X
b11 <
b11 ]
b11 f
b11 [
b11 C
b11 l
b0 Y
b0 =
b0 P
b0 h
b0 q
b0 (
b0 E
b0 A
b0 j
b10111 W
b10111 5
b10111 O
b10111 n
b10111 $
b10111 6
b10 U
b10 3
b10 d
b1011100000010000110000011 S
b1011100000010000110000011 8
b1011100000010000110000011 T
b1011100000010000110000011 %
b1011100000010000110000011 7
b10000 }
b10000 L
b10000 m
b101 Q
b101 ?
b101 R
b101 |
b101 &
b101 @
1*
11
#12000
0*
01
#13000
b0xxxxxxxx x
b0xxxxxxxx 2
b0xxxxxxxx z
b0xxxxxxxx '
b0xxxxxxxx D
bx t
bx I
bx v
bx y
bx "
bx .
b101 p
b101 J
b101 s
0\
0K
b11 [
b11 C
b11 l
b11 Y
bx =
bx P
bx h
bx q
bx (
bx E
b11 A
b11 j
b101 W
b101 5
b101 O
b101 n
b101 $
b101 6
b0 U
b0 3
b0 d
b10100011000000110000011 S
b10100011000000110000011 8
b10100011000000110000011 T
b10100011000000110000011 %
b10100011000000110000011 7
b110 Q
b110 ?
b110 R
b110 |
b110 &
b110 @
bx }
bx L
bx m
1*
11
#14000
0*
01
#15000
1b
1;
0`
09
0c
0G
bx a
bx :
bx N
bx {
b101 Z
b111 >
b111 i
b111 o
b111 w
b111 )
b111 F
b101 B
b101 k
1\
1K
b100011 X
b100011 <
b100011 ]
b100011 f
bx [
bx C
bx l
b11 Y
b11 A
b11 j
b101 W
b101 5
b101 O
b101 n
b101 $
b101 6
b10 U
b10 3
b10 d
b10100011010001010100011 S
b10100011010001010100011 8
b10100011010001010100011 T
b10100011010001010100011 %
b10100011010001010100011 7
b0xxxxxxxx }
b0xxxxxxxx L
b0xxxxxxxx m
bx =
bx P
bx h
bx q
bx (
bx E
b111 Q
b111 ?
b111 R
b111 |
b111 &
b111 @
1*
11
#16000
0*
01
#17000
b11010 p
b11010 J
b11010 s
0\
0K
b10 Z
b100 >
b100 i
b100 o
b100 w
b100 )
b100 F
b10 B
b10 k
b1 Y
b1 A
b1 j
b11010 W
b11010 5
b11010 O
b11010 n
b11010 $
b11010 6
b0 U
b0 3
b0 d
b1000001000110100100011 S
b1000001000110100100011 8
b1000001000110100100011 T
b1000001000110100100011 %
b1000001000110100100011 7
b11100 t
b11100 I
b11100 v
b11100 y
b11100 "
b11100 .
b1000 Q
b1000 ?
b1000 R
b1000 |
b1000 &
b1000 @
b10 =
b10 P
b10 h
b10 q
b10 (
b10 E
1*
11
#18000
0*
01
#19000
1_
10
0b
0;
0^
0/
b1 t
b1 I
b1 v
b1 y
b1 "
b1 .
bx p
bx J
bx s
b110 g
b110 -
b110 r
b110 !
b110 ,
1\
1K
b1100011 X
b1100011 <
b1100011 ]
b1100011 f
b10000 Z
bx >
bx i
bx o
bx w
bx )
bx F
b10000 B
b10000 k
b10 Y
b100 =
b100 P
b100 h
b100 q
b100 (
b100 E
b10 A
b10 j
b10 W
b10 5
b10 O
b10 n
b10 $
b10 6
b0 U
b0 3
b0 d
b1000000010000001001100011 S
b1000000010000001001100011 8
b1000000010000001001100011 T
b1000000010000001001100011 %
b1000000010000001001100011 7
b1001 Q
b1001 ?
b1001 R
b1001 |
b1001 &
b1001 @
1*
11
#20000
0*
01
#21000
bx X
bx <
bx ]
bx f
bx Z
bx B
bx k
bx Y
bx =
bx P
bx h
bx q
bx (
bx E
bx A
bx j
b0 W
b0 5
b0 O
b0 n
b0 $
b0 6
bx U
bx 3
bx d
bx S
bx 8
bx T
bx %
bx 7
b1011 Q
b1011 ?
b1011 R
b1011 |
b1011 &
b1011 @
1*
11
