mem_to_reg_mux/mem_mux.v
`timescale 1ns/1ps


module mem_mux(clk,mem_to_reg,alu_result,mem_data,pc,out);
input clk;
input [1:0]mem_to_reg;
input [31:0] alu_result;
input [31:0] mem_data;
input [9:0]pc;
output reg [31:0] out;

always @(posedge clk) begin
    if(mem_to_reg==1)
        out=mem_data;
    else if(mem_to_reg==0)
        out=alu_result;
    else if(mem_to_reg==2 || mem_to_reg==3)
        out=pc+1;//pc+4
end


endmodule

data_memory/data_memory.v
`timescale 1ns / 1ps

module data_memory(read_data,size,clk,address,write_data,mem_rd,mem_wr);
input clk;
input size;
input [31:0] address;
input [31:0] write_data;
input mem_rd;
input mem_wr;

reg [7:0] memory[1023:0];// 1023 locations of 4 bytes == 1024 bytes totals.
output reg [31:0] read_data;

always@(posedge clk)begin
	case(size)
	0:begin
	if(mem_rd==1)
		read_data=memory[address];
	if(mem_wr==1)
		memory[address]=write_data;
	end
	1:
	begin
		if(mem_rd==1)
		read_data[7:0]=memory[address];
		read_data[15:8]=memory[address+1];
		read_data[23:16]=memory[address+2];
		read_data[31:024]=memory[address+3];
		if(mem_wr==1)
		memory[address]=write_data[7:0];
		memory[address+1]=write_data[15:8];
		memory[address+2]=write_data[23:16];
		memory[address+3]=write_data[31:24];
	end
	endcase
end

endmodule

ALU/alu.v
`timescale 1ns / 1ps


module alu(clk,a,b,out,alu_control,zero_flag);//s is ALU CONTROL
input clk;
input [31:0] a,b;
input [2:0] alu_control;
output reg zero_flag;
output reg [31:0] out;

always@(*)
begin
	case(alu_control)
	3'b000:
		out=a&b;
	3'b001:
		out=a|b;	
	3'b010:
		out=a+b;
	3'b011:
		out=a-b;
	3'b100:
    begin
        if(a<b)
            out=0;
        else 
            out=1; 
    end
	3'b101:
	 begin
        if(a>=b)
            out=0;
        else 
            out=1; 
    end
	3'b110:
	 begin
        if(a==b)
            out=0;
        else 
            out=1; 
    end
	endcase

    if(out==0)
        zero_flag=1;
    else
        zero_flag=0;
end 
endmodule

alu_src_mux/alu_mux.v
`timescale 1ns/1ps

module alu_mux (clk,alu_src,reg2,imm,out);

input clk;
input alu_src;
input [31:0] reg2;
input [20:0]imm;
output reg [31:0] out;

always @(posedge clk) begin
    if(alu_src==1)
        out=imm;
    else if(alu_src==0)
        out=reg2;
end
    
endmodule

reg_file/reg_file.v
`timescale 1ns / 1ps

module reg_file (
input clk,wr,
input [4:0] r1,r2,rd, //5bit reg address of  the 3 registers for R-type
input [31:0] write_data,// data written into destination register
output reg [31:0] out1,out2// 
);

reg [31:0] registers [31:0];// 32 registers of 32 bit

always@(posedge clk)begin


    if(wr)
        registers[rd]<=write_data;
    else begin
        out1<=registers[r1];
        out2<=registers[r2];
    end
        
end

endmodule

alu_control/alu_control.v
`timescale 1ns / 1ps

module alu_control(clk,func3,func7,opcode,alu_control);
input clk;
input [2:0] func3;
input [6:0] func7;
input [6:0]opcode;
output reg [2:0] alu_control;

parameter r_type=7'b0110011;// add sub etc
parameter s_type=7'b0100011;//sw sb
parameter i_type=7'b0010011;// addi
parameter l_type=7'b0000011;//lw lb
parameter b_type=7'b1100011;//beq bge blt
parameter jal_type=7'b1101111;// jal
parameter jalr_type=7'b1100111;//jalr

always @(posedge clk) begin
    case(opcode)
    r_type:
    begin
        if(func3==3'b111 && func7==7'b0)//and
            alu_control=3'b000;
        else if(func3==3'b110 && func7==7'b0)//or
            alu_control=3'b001;
        else if(func3==3'b0 && func7==7'b0)//add
            alu_control=3'b010;
        else if(func3==3'b0 && func7==7'b0100000)//sub
            alu_control=3'b011;
    end
    s_type:
        alu_control=3'b010;
    i_type:
        alu_control=3'b010;
    l_type:
        alu_control=3'b010;
    b_type:
        begin
            if(func3==3'b100)//blt
                alu_control=3'b100;

            else if(func3==3'b010)//bge
                alu_control=3'b101;
                
            else if(func3==3'b000)//beq
                alu_control=3'b110;
        end
    jal_type:
        alu_control=3'b010;
    jalr_type:
        alu_control=3'b010;
    endcase
end
    
endmodule

control/control.v
`timescale 1ns / 1ps

module control(alu_src,branch,mem_read,mem_to_reg,reg_write,mem_write,alu_op,opcode, clk);
input clk;
input  [6:0] opcode;
output reg alu_src,branch,mem_read,reg_write,mem_write;
output reg [2:0]alu_op;
output reg [1:0]mem_to_reg;// for adding jal and jalr

parameter r_type=7'b0110011;// add sub etc
parameter s_type=7'b0100011;//sw sb
parameter i_type=7'b0010011;// addi
parameter l_type=7'b0000011;//lw lb
parameter b_type=7'b1100011;//beq bge blt
parameter jal_type=7'b1101111;// jal
parameter jalr_type=7'b1100111;//jalr

always@(posedge clk or opcode)begin
	case(opcode)
	r_type:begin
		alu_src=0;
		mem_to_reg=2'b00;
		reg_write=1;
		mem_read=0;
		mem_write=0;
		branch=0;
		alu_op=2'b10;
	end
	s_type:begin
		alu_src=1;
		mem_to_reg=2'bxx;
		reg_write=0;
		mem_read=0;
		mem_write=1;
		branch=0;
		alu_op=2'b00;
	end

    i_type:begin
		alu_src=1;
		mem_to_reg=2'b00;
		reg_write=1;
		mem_read=0;
		mem_write=0;
		branch=0;
		alu_op=2'b00;
	end


	l_type:begin
		alu_src=1;
		mem_to_reg=2'b01;
		reg_write=1;
		mem_read=1;
		mem_write=0;
		branch=0;
		alu_op=2'b00;
	end
	
	b_type:begin
		alu_src=0;
		mem_to_reg=2'bxx;
		reg_write=0;
		mem_read=0;
		mem_write=0;
		branch=1;
		alu_op=2'b01;
	end
    jal_type:
    begin
        alu_src=0;
		mem_to_reg=2'b10;
		reg_write=1;
		mem_read=0;
		mem_write=0;
		branch=1;
		alu_op=2'b11;
    end
    jalr_type:
    begin
        alu_src=1;
		mem_to_reg=2'b11;
		reg_write=1;
		mem_read=0;
		mem_write=0;
		branch=1;
		alu_op=2'b11;
    end

	endcase
end

endmodule

Decoder/decoder.v
`timescale 1ns / 1ps

module decoder(clk,instruction,func3,func7,opcode,r1,r2,rd,imm,size);

input clk;
input [31:0] instruction;// instruction 32 bit
output reg [2:0] func3;//func3 part
output reg [6:0] func7;// func7 part
output reg [6:0] opcode;//opcode part
output reg [4:0] r1,r2,rd;// address of r1,r2,rd
output reg [20:0] imm;//maximum imm can be 20 
output reg size; //size for lw or Lb

parameter r_type=7'b0110011;// add sub etc
parameter s_type=7'b0100011;//sw sb
parameter i_type=7'b0010011;// addi
parameter l_type=7'b0000011;//lw lb
parameter b_type=7'b1100011;//beq bge blt
parameter jal_type=7'b1101111;// jal
parameter jalr_type=7'b1100111;//jalr

always @(posedge clk) begin
    
    func3=0;func7=0;imm=0;r1=0;r2=0;rd=0;// to remove garbage value
    opcode=instruction[6:0];
    size=1;//default size is word 
    case (opcode)
    r_type:
    begin
        rd=instruction[11:7];
        func3=instruction[14:12];
        r1=instruction[19:15];
        r2=instruction[24:20];
        func7=instruction[31:25];
    end
    s_type:
        begin
            imm[4:0]=instruction[11:7];
            func3=instruction[14:12];
            r1=instruction[19:15];
            r2=instruction[24:20];
            imm[11:5]=instruction[31:25];


            if(func3==3'b000)
                size=0;
        end
    i_type:
    begin
        rd=instruction[11:7];
        func3=instruction[14:12];
        r1=instruction[19:15];
        func7=7'bx;
        imm[11:0]=instruction[31:20];
    end
    l_type:
    begin
        rd=instruction[11:7];
        func3=instruction[14:12];
        r1=instruction[19:15];
        func7=7'bx;
        imm[11:0]=instruction[31:20];
        if(func3==3'b000)
                size=0;
    end
    b_type:// shifted right once
    begin
        
        imm[11]=instruction[7];
        imm[4:1]=instruction[11:8];
        func3=instruction[14:12];
        r1=instruction[19:15];
        r2=instruction[24:20];
        imm[10:5]=instruction[30:25];
        imm[12]=instruction[31];

        imm=imm>>>1;//signed right shift
        rd=5'bx;
        func7=7'bx;
    end
    jal_type:begin
        
        rd=instruction[11:7];
        imm[19:12]=instruction[19:12];
        imm[11]=instruction[20];
        imm[10:1]=instruction[30:21];
        imm[20]=instruction[31];

        imm=imm>>>1;//signed right shift
        func3=3'bx;
        r1=5'bx;
        r2=5'bx;
        func7=7'bx;
    end
    jalr_type:
    begin
        rd=instruction[11:7];
        func3=instruction[14:12];
        r1=instruction[19:15];
        func7=7'bx;
        imm[11:0]=instruction[31:20];
    end
    endcase
end
    
endmodule

Instruction_memory/instruction_memory.v
module instruction_memory(clk,read_addr,instruction);
input clk;
input [9:0] read_addr;
output reg [31:0] instruction;
reg [31:0] imemory [1023:0];


always@(*)
begin
	//fill with instructions
    imemory[0] = 32'b00000000001000001000000010110011;   // add x1 x1 x2
    imemory[1] = 32'b01000000001100010000000100110011;   // sub x2 x2 x3
    imemory[2] = 32'b00000000000100100111001000110011;   // and x4 x4 x1
    imemory[3] = 32'b00000000010100011110000110110011;   // or x3 x3 x5
    imemory[4] = 32'b00000000110000010000001000010011;   // addi x4 x2 12
    imemory[5] = 32'b00000001011100000010000110000011;   // lw x3 23(x0)
    imemory[6] = 32'b00000000010100011000000110000011;   // lb x5 5(x3)
    imemory[7] = 32'b00000000010100011010001010100011;   // sw x5 5(x3)
    imemory[8] = 32'b00000000001000001000110100100011;   // sb x6 90(x1)
    imemory[9] = 32'b00000001000000010000001001100011;   // beq x4 x2 4
	instruction=imemory[read_addr];
end

endmodule

ProgramCounter/ProgramCounter.v
`timescale 1ns / 1ps
//////////////////////////////////////////////////////////////////////////////////
// Company: 
// Engineer: 
// 
// Create Date:    12:32:37 04/10/2023 
// Design Name: 
// Module Name:    ProgramCounter 
// Project Name: 
// Target Devices: 
// Tool versions: 
// Description: 
//
// Dependencies: 
//
// Revision: 
// Revision 0.01 - File Created
// Additional Comments: 
//
//////////////////////////////////////////////////////////////////////////////////
module ProgramCounter(
input clk,reset,
input [20:0]offset,
input branch,
input [31:0]reg_out1,
input [1:0]mem_to_reg,
input zero_flag;
output reg [9:0] count
);


always@(posedge clk)begin
	if(reset)
		count=0;
	else if(branch &&zero_flag && mem_to_reg==2'bx)
		count=count+offset;
	else if(branch && mem_to_reg==2'b11 )
		count=offset+reg_out1;//immediate + register 1
	else if(branch || mem_to_reg==2'b10 )//Btype or jal
		count=count+offset;//pc + immediate
	else
		count=count+4;//pc +4

end

endmodule

Processor/processor.v
`timescale 1ns/1ps

`include "../ALU/alu.v"
`include "../alu_control/alu_control.v"
`include "../alu_src_mux/alu_mux.v"
`include "../control/control.v"
`include "../data_memory/data_memory.v"
`include "../decoder/decoder.v"
`include "../Instruction_memory/instruction_memory.v"
`include "../mem_to_reg_mux/mem_mux.v"
`include "../ProgramCounter/ProgramCounter.v"
`include "../reg_file/reg_file.v"

// module alu(clk,a,b,out,alu_control,zero_flag);//s is ALU CONTROL
// module alu_control(clk,func3,func7,opcode,alu_control);
// module alu_mux (clk,alu_src,reg2,imm,out);
// module control(alu_src,branch,mem_read,mem_to_reg,reg_write,mem_write,alu_op,opcode, clk);
// module data_memory(read_data,clk,address,write_data,mem_rd,mem_wr);
// module decoder(clk,instruction,func3,func7,opcode,r1,r2,rd,imm);
// module instruction_memory(clk,read_addr,instruction);
// module mem_mux(clk,mem_to_reg,alu_result,mem_data,pc,out);
// module ProgramCounter(input clk,reset,input [20:0]offset,input branch,input [31:0]reg_out1,input [1:0]mem_to_reg,output reg [9:0] count
// );
// module reg_file (
// input clk,wr,
// input [4:0] r1,r2,rd, //5bit reg address of  the 3 registers for R-type
// input [31:0] write_data,// data written into destination register
// output reg [31:0] out1,out2// 
// );

module processor(clk,reset,alu_result);

//inputs
input clk,reset;
output [31:0] alu_result;

assign alu_result=result;


wire [9:0] pc;
ProgramCounter PC1 (clk,reset,imm,branch,out1,mem_to_reg,zero_flag,pc);

// instruction memory output-> decoder input
wire [31:0]instruction;

instruction_memory INSTRUCTION_MEMORY(clk,pc,instruction);

//decoder outputs ->regile,control,alu_control.
wire [2:0]func3;
wire [6:0]func7;
wire [6:0]opcode;
wire [4:0]r1;
wire [4:0]r2;
wire [4:0]rd;
wire [20:0]imm;
wire size;

decoder DECODER (clk,instruction,func3,func7,opcode,r1,r2,rd,imm,size);

//control outputs

wire mem_read;
wire mem_write;
wire alu_src;
wire reg_write;
wire [1:0] mem_to_reg;
wire [2:0] alu_op;

control CONTROL (alu_src,branch,mem_read,mem_to_reg,reg_write,mem_write,alu_op,opcode,clk);

//alu control
alu_control ALU_C(clk,func3,func7,opcode,alu_op);


//regfile output
wire [31:0] out1;
wire [31:0] out2;

reg_file REG_FILE(clk,reg_write,r1,r2,rd,write_data,out1,out2);


//mux alu src
alu_mux ALU_MUX(clk,alu_src,out2,imm,out2);

//alu outputs
wire zero_flag;
wire [31:0]result;

alu ALU(clk,out1,out2,result,alu_op,zero_flag);

//data memory 
wire [31:0] data_out;
data_memory DATA_MEMORY(data_out,size,clk,result,out2,mem_read,mem_write);
//(read_data,size,clk,address,write_data,mem_rd,mem_wr
//mem to reg mux
wire[31:0]write_data;
mem_mux MEM_MUX(clk,mem_to_reg,result,data_out,pc,write_data);


endmodule

Processor/processor_tb.v
`timescale 1ns/1ps
`include "processor.v"

module processor_tb;

reg clk,reset;
wire [31:0]alu_result;

processor uut(clk,reset,alu_result);

always#1clk=~clk;
initial begin
    $dumpfile("proccessor.vcd");
    $dumpvars(0,processor_tb);

    clk=0;reset=1;#2;
    reset=0;

    #20;

    $finish;

end
    
endmodule

Processor/proccessor.vcd
$date
	Sun May 14 16:30:42 2023
$end
$version
	Icarus Verilog
$end
$timescale
	1ps
$end
$scope module processor_tb $end
$var wire 32 ! alu_result [31:0] $end
$var reg 1 " clk $end
$var reg 1 # reset $end
$scope module uut $end
$var wire 3 $ alu_op [2:0] $end
$var wire 32 % alu_result [31:0] $end
$var wire 1 & alu_src $end
$var wire 1 ' branch $end
$var wire 1 ( clk $end
$var wire 32 ) data_out [31:0] $end
$var wire 3 * func3 [2:0] $end
$var wire 7 + func7 [6:0] $end
$var wire 21 , imm [20:0] $end
$var wire 32 - instruction [31:0] $end
$var wire 1 . mem_read $end
$var wire 2 / mem_to_reg [1:0] $end
$var wire 1 0 mem_write $end
$var wire 7 1 opcode [6:0] $end
$var wire 32 2 out1 [31:0] $end
$var wire 32 3 out2 [31:0] $end
$var wire 10 4 pc [9:0] $end
$var wire 5 5 r1 [4:0] $end
$var wire 5 6 r2 [4:0] $end
$var wire 5 7 rd [4:0] $end
$var wire 1 8 reg_write $end
$var wire 1 9 reset $end
$var wire 32 : result [31:0] $end
$var wire 1 ; size $end
$var wire 32 < write_data [31:0] $end
$var wire 1 = zero_flag $end
$scope module PC1 $end
$var wire 1 ' branch $end
$var wire 1 ( clk $end
$var wire 2 > mem_to_reg [1:0] $end
$var wire 21 ? offset [20:0] $end
$var wire 32 @ reg_out1 [31:0] $end
$var wire 1 9 reset $end
$var wire 1 = zero_flag $end
$var reg 10 A count [9:0] $end
$upscope $end
$scope module INSTRUCTION_MEMORY $end
$var wire 1 ( clk $end
$var wire 10 B read_addr [9:0] $end
$var reg 32 C instruction [31:0] $end
$upscope $end
$scope module DECODER $end
$var wire 1 ( clk $end
$var wire 32 D instruction [31:0] $end
$var reg 3 E func3 [2:0] $end
$var reg 7 F func7 [6:0] $end
$var reg 21 G imm [20:0] $end
$var reg 7 H opcode [6:0] $end
$var reg 5 I r1 [4:0] $end
$var reg 5 J r2 [4:0] $end
$var reg 5 K rd [4:0] $end
$var reg 1 L size $end
$upscope $end
$scope module CONTROL $end
$var wire 1 ( clk $end
$var wire 7 M opcode [6:0] $end
$var reg 3 N alu_op [2:0] $end
$var reg 1 O alu_src $end
$var reg 1 P branch $end
$var reg 1 Q mem_read $end
$var reg 2 R mem_to_reg [1:0] $end
$var reg 1 S mem_write $end
$var reg 1 T reg_write $end
$upscope $end
$scope module ALU_C $end
$var wire 1 ( clk $end
$var wire 3 U func3 [2:0] $end
$var wire 7 V func7 [6:0] $end
$var wire 7 W opcode [6:0] $end
$var reg 3 X alu_control [2:0] $end
$upscope $end
$scope module REG_FILE $end
$var wire 1 ( clk $end
$var wire 5 Y r1 [4:0] $end
$var wire 5 Z r2 [4:0] $end
$var wire 5 [ rd [4:0] $end
$var wire 1 8 wr $end
$var wire 32 \ write_data [31:0] $end
$var reg 32 ] out1 [31:0] $end
$var reg 32 ^ out2 [31:0] $end
$upscope $end
$scope module ALU_MUX $end
$var wire 1 & alu_src $end
$var wire 1 ( clk $end
$var wire 21 _ imm [20:0] $end
$var wire 32 ` reg2 [31:0] $end
$var reg 32 a out [31:0] $end
$upscope $end
$scope module ALU $end
$var wire 32 b a [31:0] $end
$var wire 3 c alu_control [2:0] $end
$var wire 32 d b [31:0] $end
$var wire 1 ( clk $end
$var reg 32 e out [31:0] $end
$var reg 1 f zero_flag $end
$upscope $end
$scope module DATA_MEMORY $end
$var wire 32 g address [31:0] $end
$var wire 1 ( clk $end
$var wire 1 . mem_rd $end
$var wire 1 0 mem_wr $end
$var wire 1 ; size $end
$var wire 32 h write_data [31:0] $end
$var reg 32 i read_data [31:0] $end
$upscope $end
$scope module MEM_MUX $end
$var wire 32 j alu_result [31:0] $end
$var wire 1 ( clk $end
$var wire 32 k mem_data [31:0] $end
$var wire 2 l mem_to_reg [1:0] $end
$var wire 10 m pc [9:0] $end
$var reg 32 n out [31:0] $end
$upscope $end
$upscope $end
$upscope $end
$enddefinitions $end
#0
$dumpvars
bx n
bx m
bx l
bx k
bx j
bx i
bx h
bx g
xf
bx e
bx d
bx c
bx b
bx a
bx `
bx _
bx ^
bx ]
bx \
bx [
bx Z
bx Y
bx X
bx W
bx V
bx U
xT
xS
bx R
xQ
xP
xO
bx N
bx M
xL
bx K
bx J
bx I
bx H
bx G
bx F
bx E
bx D
bx C
bx B
bx A
bx @
bx ?
bx >
x=
bx <
x;
bx :
19
x8
bx 7
bx 6
bx 5
bx 4
bx 3
bx 2
bx 1
x0
bx /
x.
bx -
bx ,
bx +
bx *
bx )
0(
x'
x&
bx %
bx $
1#
0"
bx !
$end
#1000
b0 A
b0 4
b0 B
b0 m
1L
1;
b0 K
b0 7
b0 [
b0 J
b0 6
b0 Z
b0 I
b0 5
b0 Y
b0 G
b0 ,
b0 ?
b0 _
b0 F
b0 +
b0 V
b0 E
b0 *
b0 U
0f
0=
1"
1(
#2000
0"
0(
0#
09
#3000
bx i
b100 A
b100 4
b100 B
b100 m
1"
1(
#4000
0"
0(
#5000
b1000 A
b1000 4
b1000 B
b1000 m
bx i
1"
1(
#6000
0"
0(
#7000
bx i
b1100 A
b1100 4
b1100 B
b1100 m
1"
1(
#8000
0"
0(
#9000
b10000 A
b10000 4
b10000 B
b10000 m
bx i
1"
1(
#10000
0"
0(
#11000
bx i
b10100 A
b10100 4
b10100 B
b10100 m
1"
1(
#12000
0"
0(
#13000
b11000 A
b11000 4
b11000 B
b11000 m
bx i
1"
1(
#14000
0"
0(
#15000
bx i
b11100 A
b11100 4
b11100 B
b11100 m
1"
1(
#16000
0"
0(
#17000
b100000 A
b100000 4
b100000 B
b100000 m
bx i
1"
1(
#18000
0"
0(
#19000
bx i
b100100 A
b100100 4
b100100 B
b100100 m
1"
1(
#20000
0"
0(
#21000
b101000 A
b101000 4
b101000 B
b101000 m
bx i
1"
1(
