mem_to_reg_mux/mem_mux.v
`timescale 1ns/1ps


module mem_mux(clk,mem_to_reg,alu_result,mem_data,pc,out);
input clk;
input [1:0]mem_to_reg;
input [31:0] alu_result;
input [31:0] mem_data;
input [9:0]pc;
output reg [31:0] out;

always @(posedge clk) begin
    if(mem_to_reg==1)
        out=mem_data;
    else if(mem_to_reg==0)
        out=alu_result;
    else if(mem_to_reg==2 || mem_to_reg==3)
        out=pc+4;//pc+4
end


endmodule

data_memory/data_memory.v
`timescale 1ns / 1ps

module data_memory(read_data,size,clk,address,write_data,mem_rd,mem_wr);
input clk;
input size;
input [31:0] address;
input [31:0] write_data;
input mem_rd;
input mem_wr;

reg [7:0] memory[1023:0];// 1023 locations of 4 bytes == 1024 bytes totals.
output reg [31:0] read_data;

always@(*)begin


	memory[0]=8'h02;
	memory[1]=8'h02;
	memory[2]=8'h02;
	memory[3]=8'h02;

	memory[4]=9;
	memory[5]=7;
	memory[6]=2;
	memory[7]=6;

	memory[10]=99;

	case(size)
	0:begin
	if(mem_rd==1)
		read_data=memory[address];
	if(mem_wr==1)
		memory[address]=write_data;
	end
	1:
	begin
		if(mem_rd==1)
		read_data[7:0]=memory[address];
		read_data[15:8]=memory[address+1];
		read_data[23:16]=memory[address+2];
		read_data[31:24]=memory[address+3];
		if(mem_wr==1)
		memory[address]=write_data[7:0];
		memory[address+1]=write_data[15:8];
		memory[address+2]=write_data[23:16];
		memory[address+3]=write_data[31:24];
	end
	endcase
end

endmodule

ALU/alu.v
`timescale 1ns / 1ps


module alu(clk,a,b,out,alu_control,zero_flag);//s is ALU CONTROL
input clk;
input [31:0] a,b;
input [2:0] alu_control;
output reg zero_flag;
output reg [31:0] out;

always@(*)
begin
	case(alu_control)
	3'b000:
		out=a&b;
	3'b001:
		out=a|b;	
	3'b010:
		out=a+b;
	3'b011:
		out=a-b;
	3'b100:
    begin
        if(a<b)
            out=0;
        else 
            out=1; 
    end
	3'b101:
	 begin
        if(a>=b)
            out=0;
        else 
            out=1; 
    end
	3'b110:
	 begin
        if(a==b)
            out=0;
        else 
            out=1; 
    end
	endcase

    if(out==0)
        zero_flag=1;
    else
        zero_flag=0;
end 
endmodule

alu_src_mux/alu_mux.v
`timescale 1ns/1ps

module alu_mux (clk,alu_src,reg2,imm,out);

input clk;
input alu_src;
input [31:0] reg2;
input [20:0]imm;
output reg [31:0] out;

always @(posedge clk) begin
    if(alu_src==1)
        out=imm;
    else if(alu_src==0)
        out=reg2;
end
    
endmodule

reg_file/reg_file.v
`timescale 1ns / 1ps

module reg_file (
input clk,wr,
input [4:0] r1,r2,rd, //5bit reg address of  the 3 registers for R-type
input [31:0] write_data,// data written into destination register
output reg [31:0] out1,out2// 
);

reg [31:0] registers [31:0];// 32 registers of 32 bit

always@(posedge clk)begin


    if(wr)
        registers[rd]<=write_data;
    else begin
        out1<=registers[r1];
        out2<=registers[r2];
    end
        
end

endmodule

alu_control/alu_control.v
`timescale 1ns / 1ps

module alu_control(clk,func3,func7,opcode,alu_control);
input clk;
input [2:0] func3;
input [6:0] func7;
input [6:0]opcode;
output reg [2:0] alu_control;

parameter r_type=7'b0110011;// add sub etc
parameter s_type=7'b0100011;//sw sb
parameter i_type=7'b0010011;// addi
parameter l_type=7'b0000011;//lw lb
parameter b_type=7'b1100011;//beq bge blt
parameter jal_type=7'b1101111;// jal
parameter jalr_type=7'b1100111;//jalr

always @(posedge clk) begin
    case(opcode)
    r_type:
    begin
        if(func3==3'b111 && func7==7'b0)//and
            alu_control=3'b000;
        else if(func3==3'b110 && func7==7'b0)//or
            alu_control=3'b001;
        else if(func3==3'b0 && func7==7'b0)//add
            alu_control=3'b010;
        else if(func3==3'b0 && func7==7'b0100000)//sub
            alu_control=3'b011;
    end
    s_type:
        alu_control=3'b010;
    i_type:
        alu_control=3'b010;
    l_type:
        alu_control=3'b010;
    b_type:
        begin
            if(func3==3'b100)//blt
                alu_control=3'b100;

            else if(func3==3'b010)//bge
                alu_control=3'b101;
                
            else if(func3==3'b000)//beq
                alu_control=3'b110;
        end
    jal_type:
        alu_control=3'b010;
    jalr_type:
        alu_control=3'b010;
    endcase
end
    
endmodule

control/control.v
`timescale 1ns / 1ps

module control(alu_src,branch,mem_read,mem_to_reg,reg_write,mem_write,opcode, clk);
input clk;
input  [6:0] opcode;
output reg alu_src,branch,mem_read,reg_write,mem_write;
output reg [1:0]mem_to_reg;// for adding jal and jalr

parameter r_type=7'b0110011;// add sub etc
parameter s_type=7'b0100011;//sw sb
parameter i_type=7'b0010011;// addi
parameter l_type=7'b0000011;//lw lb
parameter b_type=7'b1100011;//beq bge blt
parameter jal_type=7'b1101111;// jal
parameter jalr_type=7'b1100111;//jalr

always@(*)begin
	case(opcode)
	r_type:begin
		alu_src=0;
		mem_to_reg=2'b00;
		reg_write=1;
		mem_read=0;
		mem_write=0;
		branch=0;
	end
	s_type:begin
		alu_src=1;
		mem_to_reg=2'bxx;
		reg_write=0;
		mem_read=0;
		mem_write=1;
		branch=0;
	end

    i_type:begin
		alu_src=1;
		mem_to_reg=2'b00;
		reg_write=1;
		mem_read=0;
		mem_write=0;
		branch=0;
	end


	l_type:begin
		alu_src=1;
		mem_to_reg=2'b01;
		reg_write=1;
		mem_read=1;
		mem_write=0;
		branch=0;
	end
	
	b_type:begin
		alu_src=0;
		mem_to_reg=2'bx;
		reg_write=0;
		mem_read=0;
		mem_write=0;
		branch=1;
	end
    jal_type:
    begin
        alu_src=0;
		mem_to_reg=2'b10;
		reg_write=1;
		mem_read=0;
		mem_write=0;
		branch=1;
    end
    jalr_type:
    begin
        alu_src=1;
		mem_to_reg=2'b11;
		reg_write=1;
		mem_read=0;
		mem_write=0;
		branch=1;
    end

	endcase
end

endmodule

Decoder/decoder.v
`timescale 1ns / 1ps

module decoder(clk,instruction,func3,func7,opcode,r1,r2,rd,imm,size);

input clk;
input [31:0] instruction;// instruction 32 bit
output reg [2:0] func3;//func3 part
output reg [6:0] func7;// func7 part
output reg [6:0] opcode;//opcode part
output reg [4:0] r1,r2,rd;// address of r1,r2,rd
output reg [20:0] imm;//maximum imm can be 20 
output reg size; //size for lw or Lb

parameter r_type=7'b0110011;// add sub etc
parameter s_type=7'b0100011;//sw sb
parameter i_type=7'b0010011;// addi
parameter l_type=7'b0000011;//lw lb
parameter b_type=7'b1100011;//beq bge blt
parameter jal_type=7'b1101111;// jal
parameter jalr_type=7'b1100111;//jalr

always @(posedge clk) begin
    
    func3=0;func7=0;imm=0;r1=0;r2=0;rd=0;// to remove garbage value
    opcode=instruction[6:0];
    size=1;//default size is word 
    case (opcode)
    r_type:
    begin
        rd=instruction[11:7];
        func3=instruction[14:12];
        r1=instruction[19:15];
        r2=instruction[24:20];
        func7=instruction[31:25];
    end
    s_type:
        begin
            imm[4:0]=instruction[11:7];
            func3=instruction[14:12];
            r1=instruction[19:15];
            r2=instruction[24:20];
            imm[11:5]=instruction[31:25];


            if(func3==3'b000)
                size=0;
        end
    i_type:
    begin
        rd=instruction[11:7];
        func3=instruction[14:12];
        r1=instruction[19:15];
        func7=7'bx;
        imm[11:0]=instruction[31:20];
    end
    l_type:
    begin
        rd=instruction[11:7];
        func3=instruction[14:12];
        r1=instruction[19:15];
        func7=7'bx;
        imm[11:0]=instruction[31:20];
        if(func3==3'b000)
                size=0;
    end
    b_type:// shifted right once
    begin
        
        imm[11]=instruction[7];
        imm[4:1]=instruction[11:8];
        func3=instruction[14:12];
        r1=instruction[19:15];
        r2=instruction[24:20];
        imm[10:5]=instruction[30:25];
        imm[12]=instruction[31];

        imm=imm>>>1;//signed right shift
        rd=5'bx;
        func7=7'bx;
    end
    jal_type:begin
        
        rd=instruction[11:7];
        imm[19:12]=instruction[19:12];
        imm[11]=instruction[20];
        imm[10:1]=instruction[30:21];
        imm[20]=instruction[31];

        imm=imm>>>1;//signed right shift
        func3=3'bx;
        r1=5'bx;
        r2=5'bx;
        func7=7'bx;
    end
    jalr_type:
    begin
        rd=instruction[11:7];
        func3=instruction[14:12];
        r1=instruction[19:15];
        func7=7'bx;
        imm[11:0]=instruction[31:20];
    end
    endcase
end
    
endmodule

Instruction_memory/instruction_memory.v
module instruction_memory(clk,read_addr,instruction);
input clk;
input [9:0] read_addr;
output reg [31:0] instruction;
reg [31:0] imemory [1023:0];


always@(*)
begin
	imemory[0] = 32'b00000000001000001000000010110011; // add x1 x1 x2
    imemory[1] = 32'b01000000001100010000000100110011; // sub x2 x2 x3
    imemory[2] = 32'b00000000010100011110000110110011; // or x3 x3 x5
    imemory[3] = 32'b00000000000100100111001000110011; // and x4 x4 x1
    imemory[4] = 32'b00000000010100011000000110000011; // lb x5 5(x3)
    imemory[5] = 32'b00000000010000010000001001100011; // beq x4 x2 1
	instruction=imemory[read_addr];
end

endmodule

ProgramCounter/ProgramCounter.v
`timescale 1ns / 1ps
//////////////////////////////////////////////////////////////////////////////////
// Company: 
// Engineer: 
// 
// Create Date:    12:32:37 04/10/2023 
// Design Name: 
// Module Name:    ProgramCounter 
// Project Name: 
// Target Devices: 
// Tool versions: 
// Description: 
//
// Dependencies: 
//
// Revision: 
// Revision 0.01 - File Created
// Additional Comments: 
//
//////////////////////////////////////////////////////////////////////////////////
module ProgramCounter(
input clk,reset,
input [20:0]offset,
input branch,
input [31:0]reg_out1,
input [1:0]mem_to_reg,
input zero_flag;
output reg [9:0] count
);


always@(posedge clk)begin
	if(reset)
		count=0;
	else if(branch &&zero_flag && mem_to_reg==2'bx)
		count=count+offset;
	else if(branch && mem_to_reg==2'b11 )
		count=offset+reg_out1;//immediate + register 1
	else if(branch || mem_to_reg==2'b10 )//Btype or jal
		count=count+offset;//pc + immediate
	else
		count=count+4;//pc +4

end

endmodule

Processor/processor.v
`timescale 1ns/1ps

`include "../ALU/alu.v"
`include "../alu_control/alu_control.v"
`include "../alu_src_mux/alu_mux.v"
`include "../control/control.v"
`include "../data_memory/data_memory.v"
`include "../decoder/decoder.v"
`include "../Instruction_memory/instruction_memory.v"
`include "../mem_to_reg_mux/mem_mux.v"
`include "../ProgramCounter/ProgramCounter.v"
`include "../reg_file/reg_file.v"

// module alu(clk,a,b,out,alu_control,zero_flag);//s is ALU CONTROL
// module alu_control(clk,func3,func7,opcode,alu_control);
// module alu_mux (clk,alu_src,reg2,imm,out);
// module control(alu_src,branch,mem_read,mem_to_reg,reg_write,mem_write,alu_op,opcode, clk);
// module data_memory(read_data,clk,address,write_data,mem_rd,mem_wr);
// module decoder(clk,instruction,func3,func7,opcode,r1,r2,rd,imm);
// module instruction_memory(clk,read_addr,instruction);
// module mem_mux(clk,mem_to_reg,alu_result,mem_data,pc,out);
// module ProgramCounter(input clk,reset,input [20:0]offset,input branch,input [31:0]reg_out1,input [1:0]mem_to_reg,output reg [9:0] count
// );
// module reg_file (
// input clk,wr,
// input [4:0] r1,r2,rd, //5bit reg address of  the 3 registers for R-type
// input [31:0] write_data,// data written into destination register
// output reg [31:0] out1,out2// 
// );

module processor(clk,reset,instr,pc_out,imm_out,alu_control,reg_out1,reg_out2,alu_result,read_data);

//inputs
input clk,reset;
output [31:0] instr;
output [9:0]pc_out;
output [20:0]imm_out;
output [2:0]alu_control;
output [31:0]reg_out1;
output [31:0]reg_out2;
output [31:0]alu_result;
output [31:0]read_data;

assign instr=instruction;
assign pc_out=pc;
assign imm_out=imm;
assign alu_control=alu_op;
assign reg_out1=out1;
assign reg_out2=out2;
assign alu_result=result;
assign read_data=data_out;

wire [9:0] pc;
ProgramCounter PC1 (clk,reset,imm,branch,out1,mem_to_reg,zero_flag,pc);

// instruction memory output-> decoder input
wire [31:0]instruction;

instruction_memory INSTRUCTION_MEMORY(clk,pc,instruction);

//decoder outputs ->regile,control,alu_control.
wire [2:0]func3;
wire [6:0]func7;
wire [6:0]opcode;
wire [4:0]r1;
wire [4:0]r2;
wire [4:0]rd;
wire [20:0]imm;
wire size;

decoder DECODER (clk,instruction,func3,func7,opcode,r1,r2,rd,imm,size);

//control outputs

wire mem_read;
wire mem_write;
wire alu_src;
wire reg_write;
wire [1:0] mem_to_reg;

control CONTROL (alu_src,branch,mem_read,mem_to_reg,reg_write,mem_write,opcode,clk);

//alu control
wire [2:0]alu_op;
alu_control ALU_C(clk,func3,func7,opcode,alu_op);


//regfile output
wire [31:0] out1;
wire [31:0] out2;

reg_file REG_FILE(clk,reg_write,r1,r2,rd,write_data,out1,out2);


//mux alu src
wire [31:0]selected;
alu_mux ALU_MUX(clk,alu_src,out2,imm,selected);

//alu outputs
wire zero_flag;
wire [31:0]result;

alu ALU(clk,out1,selected,result,alu_op,zero_flag);

//data memory 
wire [31:0] data_out;
data_memory DATA_MEMORY(data_out,size,clk,result,out2,mem_read,mem_write);
//(read_data,size,clk,address,write_data,mem_rd,mem_wr
//mem to reg mux
wire[31:0]write_data;
mem_mux MEM_MUX(clk,mem_to_reg,result,data_out,pc,write_data);


endmodule

Processor/processor_tb.v
`timescale 1ns/1ps
`include "processor.v"

module processor_tb;

reg clk,reset;
wire [31:0]instr;
wire [9:0] pc_out;
wire [20:0]imm_out;
wire [2:0]alu_control;
wire [31:0]reg_out1;
wire [31:0]reg_out2;
wire [31:0]alu_result;
wire [31:0]read_data;

processor uut(clk,reset,instr,pc_out,imm_out,alu_control,reg_out1,reg_out2,alu_result,read_data);

always#1clk=~clk;
initial begin
    $dumpfile("proccessor.vcd");
    $dumpvars(0,processor_tb);

    clk=0;reset=1;#2;
    reset=0;
    #20;

    $finish;

end
    
endmodule

Processor/proccessor.vcd
$date
	Sun May 14 21:28:47 2023
$end
$version
	Icarus Verilog
$end
$timescale
	1ps
$end
$scope module processor_tb $end
$var wire 3 ! alu_control [2:0] $end
$var wire 32 " alu_result [31:0] $end
$var wire 21 # imm_out [20:0] $end
$var wire 32 $ instr [31:0] $end
$var wire 10 % pc_out [9:0] $end
$var wire 32 & read_data [31:0] $end
$var wire 32 ' reg_out1 [31:0] $end
$var wire 32 ( reg_out2 [31:0] $end
$var reg 1 ) clk $end
$var reg 1 * reset $end
$scope module uut $end
$var wire 3 + alu_control [2:0] $end
$var wire 3 , alu_op [2:0] $end
$var wire 32 - alu_result [31:0] $end
$var wire 1 . alu_src $end
$var wire 1 / branch $end
$var wire 1 0 clk $end
$var wire 32 1 data_out [31:0] $end
$var wire 3 2 func3 [2:0] $end
$var wire 7 3 func7 [6:0] $end
$var wire 21 4 imm [20:0] $end
$var wire 21 5 imm_out [20:0] $end
$var wire 32 6 instr [31:0] $end
$var wire 32 7 instruction [31:0] $end
$var wire 1 8 mem_read $end
$var wire 2 9 mem_to_reg [1:0] $end
$var wire 1 : mem_write $end
$var wire 7 ; opcode [6:0] $end
$var wire 32 < out1 [31:0] $end
$var wire 32 = out2 [31:0] $end
$var wire 10 > pc [9:0] $end
$var wire 10 ? pc_out [9:0] $end
$var wire 5 @ r1 [4:0] $end
$var wire 5 A r2 [4:0] $end
$var wire 5 B rd [4:0] $end
$var wire 32 C read_data [31:0] $end
$var wire 32 D reg_out1 [31:0] $end
$var wire 32 E reg_out2 [31:0] $end
$var wire 1 F reg_write $end
$var wire 1 G reset $end
$var wire 32 H result [31:0] $end
$var wire 32 I selected [31:0] $end
$var wire 1 J size $end
$var wire 32 K write_data [31:0] $end
$var wire 1 L zero_flag $end
$scope module PC1 $end
$var wire 1 / branch $end
$var wire 1 0 clk $end
$var wire 2 M mem_to_reg [1:0] $end
$var wire 21 N offset [20:0] $end
$var wire 32 O reg_out1 [31:0] $end
$var wire 1 G reset $end
$var wire 1 L zero_flag $end
$var reg 10 P count [9:0] $end
$upscope $end
$scope module INSTRUCTION_MEMORY $end
$var wire 1 0 clk $end
$var wire 10 Q read_addr [9:0] $end
$var reg 32 R instruction [31:0] $end
$upscope $end
$scope module DECODER $end
$var wire 1 0 clk $end
$var wire 32 S instruction [31:0] $end
$var reg 3 T func3 [2:0] $end
$var reg 7 U func7 [6:0] $end
$var reg 21 V imm [20:0] $end
$var reg 7 W opcode [6:0] $end
$var reg 5 X r1 [4:0] $end
$var reg 5 Y r2 [4:0] $end
$var reg 5 Z rd [4:0] $end
$var reg 1 [ size $end
$upscope $end
$scope module CONTROL $end
$var wire 1 0 clk $end
$var wire 7 \ opcode [6:0] $end
$var reg 1 ] alu_src $end
$var reg 1 ^ branch $end
$var reg 1 _ mem_read $end
$var reg 2 ` mem_to_reg [1:0] $end
$var reg 1 a mem_write $end
$var reg 1 b reg_write $end
$upscope $end
$scope module ALU_C $end
$var wire 1 0 clk $end
$var wire 3 c func3 [2:0] $end
$var wire 7 d func7 [6:0] $end
$var wire 7 e opcode [6:0] $end
$var reg 3 f alu_control [2:0] $end
$upscope $end
$scope module REG_FILE $end
$var wire 1 0 clk $end
$var wire 32 g out1 [31:0] $end
$var wire 32 h out2 [31:0] $end
$var wire 5 i r1 [4:0] $end
$var wire 5 j r2 [4:0] $end
$var wire 5 k rd [4:0] $end
$var wire 1 F wr $end
$var wire 32 l write_data [31:0] $end
$upscope $end
$scope module ALU_MUX $end
$var wire 1 . alu_src $end
$var wire 1 0 clk $end
$var wire 21 m imm [20:0] $end
$var wire 32 n reg2 [31:0] $end
$var reg 32 o out [31:0] $end
$upscope $end
$scope module ALU $end
$var wire 32 p a [31:0] $end
$var wire 3 q alu_control [2:0] $end
$var wire 32 r b [31:0] $end
$var wire 1 0 clk $end
$var reg 32 s out [31:0] $end
$var reg 1 t zero_flag $end
$upscope $end
$scope module DATA_MEMORY $end
$var wire 32 u address [31:0] $end
$var wire 1 0 clk $end
$var wire 1 8 mem_rd $end
$var wire 1 : mem_wr $end
$var wire 1 J size $end
$var wire 32 v write_data [31:0] $end
$var reg 32 w read_data [31:0] $end
$upscope $end
$scope module MEM_MUX $end
$var wire 32 x alu_result [31:0] $end
$var wire 1 0 clk $end
$var wire 32 y mem_data [31:0] $end
$var wire 2 z mem_to_reg [1:0] $end
$var wire 10 { pc [9:0] $end
$var reg 32 | out [31:0] $end
$upscope $end
$upscope $end
$upscope $end
$enddefinitions $end
#0
$dumpvars
bx |
bx {
bx z
bx y
bx x
bx w
bx v
bx u
xt
bx s
bx r
bx q
bx p
bx o
bx n
bx m
bx l
bx k
bx j
bx i
bx h
bx g
bx f
bx e
bx d
bx c
xb
xa
bx `
x_
x^
x]
bx \
x[
bx Z
bx Y
bx X
bx W
bx V
bx U
bx T
bx S
bx R
bx Q
bx P
bx O
bx N
bx M
xL
bx K
xJ
bx I
bx H
1G
xF
bx E
bx D
bx C
bx B
bx A
bx @
bx ?
bx >
bx =
bx <
bx ;
x:
bx 9
x8
bx 7
bx 6
bx 5
bx 4
bx 3
bx 2
bx 1
00
x/
x.
bx -
bx ,
bx +
1*
0)
bx (
bx '
bx &
bx %
bx $
bx #
bx "
bx !
$end
#1000
bx00000110xxxxxxxx 1
bx00000110xxxxxxxx y
bx00000110xxxxxxxx &
bx00000110xxxxxxxx C
b110 s
b110 H
b110 u
b110 x
b110 "
b110 -
b100 o
b100 I
b100 r
0t
0L
bx00000110xxxxxxxx w
b10 f
b10 ,
b10 q
b10 !
b10 +
0^
0/
0a
0:
0_
08
1b
1F
b0 `
b0 9
b0 M
b0 z
0]
0.
b0 U
b0 3
b0 d
b10 Y
b100 =
b100 h
b100 n
b100 v
b100 (
b100 E
b10 A
b10 j
b1 X
b10 <
b10 O
b10 g
b10 p
b10 '
b10 D
b1 @
b1 i
b0 T
b0 2
b0 c
b1 Z
b1 B
b1 k
1[
1J
b110011 W
b110011 ;
b110011 \
b110011 e
b0 V
b0 4
b0 N
b0 m
b0 #
b0 5
b1000001000000010110011 R
b1000001000000010110011 7
b1000001000000010110011 S
b1000001000000010110011 $
b1000001000000010110011 6
b0 P
b0 >
b0 Q
b0 {
b0 %
b0 ?
1)
10
#2000
0)
00
0*
0G
#3000
b101 o
b101 I
b101 r
b11 f
b11 ,
b11 q
b11 !
b11 +
b100000001000000010xxxxxxxx w
b100000001000000010xxxxxxxx 1
b100000001000000010xxxxxxxx y
b100000001000000010xxxxxxxx &
b100000001000000010xxxxxxxx C
b10 Z
b10 B
b10 k
b11 Y
b101 =
b101 h
b101 n
b101 v
b101 (
b101 E
b11 A
b11 j
b10 X
b10 @
b10 i
b100000 U
b100000 3
b100000 d
b0 T
b0 2
b0 c
b11111111111111111111111111111111 s
b11111111111111111111111111111111 H
b11111111111111111111111111111111 u
b11111111111111111111111111111111 x
b11111111111111111111111111111111 "
b11111111111111111111111111111111 -
b1000000001100010000000100110011 R
b1000000001100010000000100110011 7
b1000000001100010000000100110011 S
b1000000001100010000000100110011 $
b1000000001100010000000100110011 6
b110 |
b110 K
b110 l
b100 <
b100 O
b100 g
b100 p
b100 '
b100 D
b1 P
b1 >
b1 Q
b1 {
b1 %
b1 ?
1)
10
#4000
0)
00
#5000
b111 o
b111 I
b111 r
b1 f
b1 ,
b1 q
b1 !
b1 +
b11 Z
b11 B
b11 k
b101 Y
b111 =
b111 h
b111 n
b111 v
b111 (
b111 E
b101 A
b101 j
b11 X
b11 @
b11 i
b0 U
b0 3
b0 d
b110 T
b110 2
b110 c
b11000110000000000000000xxxxxxxx w
b11000110000000000000000xxxxxxxx 1
b11000110000000000000000xxxxxxxx y
b11000110000000000000000xxxxxxxx &
b11000110000000000000000xxxxxxxx C
b10100011110000110110011 R
b10100011110000110110011 7
b10100011110000110110011 S
b10100011110000110110011 $
b10100011110000110110011 6
b111 s
b111 H
b111 u
b111 x
b111 "
b111 -
b10 P
b10 >
b10 Q
b10 {
b10 %
b10 ?
b101 <
b101 O
b101 g
b101 p
b101 '
b101 D
b11111111111111111111111111111111 |
b11111111111111111111111111111111 K
b11111111111111111111111111111111 l
1)
10
#6000
0)
00
#7000
1t
1L
b10 o
b10 I
b10 r
b0 f
b0 ,
b0 q
b0 !
b0 +
b100000001000000010xxxxxxxx w
b100000001000000010xxxxxxxx 1
b100000001000000010xxxxxxxx y
b100000001000000010xxxxxxxx &
b100000001000000010xxxxxxxx C
b100 Z
b100 B
b100 k
b1 Y
b10 =
b10 h
b10 n
b10 v
b10 (
b10 E
b1 A
b1 j
b100 X
b100 @
b100 i
b0 U
b0 3
b0 d
b111 T
b111 2
b111 c
b0 s
b0 H
b0 u
b0 x
b0 "
b0 -
b100100111001000110011 R
b100100111001000110011 7
b100100111001000110011 S
b100100111001000110011 $
b100100111001000110011 6
b111 |
b111 K
b111 l
b100 <
b100 O
b100 g
b100 p
b100 '
b100 D
b11 P
b11 >
b11 Q
b11 {
b11 %
b11 ?
1)
10
#8000
0)
00
#9000
b1100011 w
b1100011 1
b1100011 y
b1100011 &
b1100011 C
1_
18
b1 `
b1 9
b1 M
b1 z
1]
1.
b101 o
b101 I
b101 r
0t
0L
b1010 s
b1010 H
b1010 u
b1010 x
b1010 "
b1010 -
b10 f
b10 ,
b10 q
b10 !
b10 +
0[
0J
b101 V
b101 4
b101 N
b101 m
b101 #
b101 5
b11 W
b11 ;
b11 \
b11 e
b11 Z
b11 B
b11 k
bx Y
bx =
bx h
bx n
bx v
bx (
bx E
bx A
bx j
b11 X
b11 @
b11 i
bx U
bx 3
bx d
b0 T
b0 2
b0 c
b10100011000000110000011 R
b10100011000000110000011 7
b10100011000000110000011 S
b10100011000000110000011 $
b10100011000000110000011 6
b100 P
b100 >
b100 Q
b100 {
b100 %
b100 ?
b101 <
b101 O
b101 g
b101 p
b101 '
b101 D
b0 |
b0 K
b0 l
1)
10
#10000
0)
00
#11000
1t
1L
1^
1/
0_
08
0b
0F
bx `
bx 9
bx M
bx z
0]
0.
b100 o
b100 I
b100 r
b110 f
b110 ,
b110 q
b110 !
b110 +
b10000000100000001000000111 w
b10000000100000001000000111 1
b10000000100000001000000111 y
b10000000100000001000000111 &
b10000000100000001000000111 C
b100 Y
b100 =
b100 h
b100 n
b100 v
b100 (
b100 E
b100 A
b100 j
1[
1J
b1100011 W
b1100011 ;
b1100011 \
b1100011 e
bx Z
bx B
bx k
b10 X
b10 @
b10 i
b10 V
b10 4
b10 N
b10 m
b10 #
b10 5
b0 T
b0 2
b0 c
b0 s
b0 H
b0 u
b0 x
b0 "
b0 -
b10000010000001001100011 R
b10000010000001001100011 7
b10000010000001001100011 S
b10000010000001001100011 $
b10000010000001001100011 6
b1100011 |
b1100011 K
b1100011 l
b100 <
b100 O
b100 g
b100 p
b100 '
b100 D
b101 P
b101 >
b101 Q
b101 {
b101 %
b101 ?
1)
10
#12000
0)
00
#13000
b1001000000100000001000000111 1
b1001000000100000001000000111 y
b1001000000100000001000000111 &
b1001000000100000001000000111 C
b1001000000100000001000000111 w
0t
0L
b1 s
b1 H
b1 u
b1 x
b1 "
b1 -
bx o
bx I
bx r
bx W
bx ;
bx \
bx e
bx Y
bx =
bx h
bx n
bx v
bx (
bx E
bx A
bx j
bx X
bx <
bx O
bx g
bx p
bx '
bx D
bx @
bx i
b0 V
b0 4
b0 N
b0 m
b0 #
b0 5
bx T
bx 2
bx c
bx R
bx 7
bx S
bx $
bx 6
b111 P
b111 >
b111 Q
b111 {
b111 %
b111 ?
1)
10
