control/control.v
`timescale 1ns / 1ps

module control(alu_src,branch,mem_read,mem_to_reg,reg_write,mem_write,alu_op,opcode, clk);
input clk;
input  [6:0] opcode;
output reg alu_src,branch,mem_read,reg_write,mem_write;
output reg [1:0]alu_op;
output reg [1:0]mem_to_reg;// for adding jal and jalr

parameter r_type=7'b0110011;// add sub etc
parameter s_type=7'b0100011;//sw sb
parameter i_type=7'b0010011;// addi
parameter l_type=7'b0000011;//lw lb
parameter b_type=7'b1100011;//beq bge blt
parameter jal_type=7'b1101111;// jal
parameter jalr_type=7'b1100111;//jalr

always@(posedge clk or opcode)begin
	case(opcode)
	r_type:begin
		alu_src=0;
		mem_to_reg=2'b00;
		reg_write=1;
		mem_read=0;
		mem_write=0;
		branch=0;
		alu_op=2'b10;
	end
	s_type:begin
		alu_src=1;
		mem_to_reg=2'bxx;
		reg_write=0;
		mem_read=0;
		mem_write=1;
		branch=0;
		alu_op=2'b00;
	end

    i_type:begin
		alu_src=1;
		mem_to_reg=2'b00;
		reg_write=1;
		mem_read=0;
		mem_write=0;
		branch=0;
		alu_op=2'b00;
	end


	l_type:begin
		alu_src=1;
		mem_to_reg=2'b01;
		reg_write=1;
		mem_read=1;
		mem_write=0;
		branch=0;
		alu_op=2'b00;
	end
	
	b_type:begin
		alu_src=0;
		mem_to_reg=2'bxx;
		reg_write=0;
		mem_read=0;
		mem_write=0;
		branch=1;
		alu_op=2'b01;
	end
    jal_type:
    begin
        alu_src=0;
		mem_to_reg=2'b00;
		reg_write=1;
		mem_read=0;
		mem_write=0;
		branch=1;
		alu_op=2'b11;
    end
    jalr_type:
    begin
        alu_src=1;
		mem_to_reg=2'b00;
		reg_write=1;
		mem_read=0;
		mem_write=0;
		branch=1;
		alu_op=2'b11;
    end

	endcase
end

endmodule

control/control_tb.v
`timescale 1ns / 1ps
`include"control.v"

module control_tb;
    
    reg clk;
    reg  [6:0] opcode;
    wire alu_src,branch,mem_read,reg_write,mem_write;
    wire [1:0]alu_op;
    wire [1:0]mem_to_reg;


    control uut(alu_src,branch,mem_read,mem_to_reg,reg_write,mem_write,alu_op,opcode, clk);

always#1clk=~clk;
    initial begin
        $dumpfile("control.vcd");
        $dumpvars(0,control_tb);
        clk=0;#1;
        opcode=7'b0110011;#2;// add sub etc
        opcode=7'b0100011;#2;//sw sb
        opcode=7'b0010011;#2;// addi
        opcode=7'b0000011;#2;//lw lb
        opcode=7'b1100011;#2;//beq bge blt
        opcode=7'b1101111;#2;// jal
        opcode=7'b1100111;#2;//jalr


        $finish;
    end
endmodule

control/control.vcd
$date
	Sat May 13 23:39:57 2023
$end
$version
	Icarus Verilog
$end
$timescale
	1ps
$end
$scope module control_tb $end
$var wire 2 ! alu_op [1:0] $end
$var wire 1 " alu_src $end
$var wire 1 # branch $end
$var wire 1 $ mem_read $end
$var wire 2 % mem_to_reg [1:0] $end
$var wire 1 & mem_write $end
$var wire 1 ' reg_write $end
$var reg 1 ( clk $end
$var reg 7 ) opcode [6:0] $end
$scope module uut $end
$var wire 1 * clk $end
$var wire 7 + opcode [6:0] $end
$var reg 2 , alu_op [1:0] $end
$var reg 1 - alu_src $end
$var reg 1 . branch $end
$var reg 1 / mem_read $end
$var reg 2 0 mem_to_reg [1:0] $end
$var reg 1 1 mem_write $end
$var reg 1 2 reg_write $end
$upscope $end
$upscope $end
$enddefinitions $end
#0
$dumpvars
x2
x1
bx 0
x/
x.
x-
bx ,
bx +
0*
bx )
0(
x'
x&
bx %
x$
x#
x"
bx !
$end
#1000
b10 ,
b10 !
0.
0#
01
0&
0/
0$
12
1'
b0 0
b0 %
0-
0"
b110011 )
b110011 +
1(
1*
#2000
0(
0*
#3000
b0 ,
b0 !
11
1&
02
0'
bx 0
bx %
1-
1"
1(
1*
b100011 )
b100011 +
#4000
0(
0*
#5000
01
0&
12
1'
b0 0
b0 %
1(
1*
b10011 )
b10011 +
#6000
0(
0*
#7000
1/
1$
b1 0
b1 %
1(
1*
b11 )
b11 +
#8000
0(
0*
#9000
b1 ,
b1 !
1.
1#
0/
0$
02
0'
bx 0
bx %
0-
0"
1(
1*
b1100011 )
b1100011 +
#10000
0(
0*
#11000
b11 ,
b11 !
12
1'
b0 0
b0 %
1(
1*
b1101111 )
b1101111 +
#12000
0(
0*
#13000
1-
1"
1(
1*
b1100111 )
b1100111 +
