data_memory/data_memory.v
`timescale 1ns / 1ps

module data_memory(read_data,size,clk,address,write_data,mem_rd,mem_wr);
input clk;
input size;
input [31:0] address;
input [31:0] write_data;
input mem_rd;
input mem_wr;

reg [7:0] memory[1023:0];// 1023 locations of 4 bytes == 1024 bytes totals.
output reg [31:0] read_data;

always@(posedge clk)begin
	case(size)
	0:begin
	if(mem_rd==1)
		read_data=memory[address];
	if(mem_wr==1)
		memory[address]=write_data;
	end
	1:
	begin
		if(mem_rd==1)
		read_data[7:0]=memory[address];
		read_data[15:8]=memory[address+1];
		read_data[23:16]=memory[address+2];
		read_data[31:024]=memory[address+3];
		if(mem_wr==1)
		memory[address]=write_data[7:0];
		memory[address+1]=write_data[15:8];
		memory[address+2]=write_data[23:16];
		memory[address+3]=write_data[31:24];
	end
	endcase
end

endmodule

data_memory/data_memory_tb.v
`timescale 1ns / 1ps
`include"data_memory.v"

module data_memory_tb;

	// Inputs
	reg clk;
	reg [31:0] address;
	reg size;
	reg [31:0] write_data;
	reg mem_rd;
	reg mem_wr;

	// Outputs
	wire [31:0] read_data;

	// Instantiate the Unit Under Test (UUT)
	data_memory uut (
		.read_data(read_data), 
		.size(size),
		.clk(clk), 
		.address(address), 
		.write_data(write_data), 
		.mem_rd(mem_rd), 
		.mem_wr(mem_wr)
	);
always#1clk=~clk;
	initial begin
		// Initialize Inputs
        $dumpfile("data_memory.vcd");
        $dumpvars(0,data_memory_tb);

		clk = 1;
		address = 0;
		write_data = 0;
		mem_rd = 0;
		mem_wr = 0;
		//byte
		size=0;
		write_data=277;
		mem_wr=1;mem_rd=0;#5// writes
		mem_rd=1;mem_wr=0;#5//reads

		//word
		address=277;
		size=1;
		mem_wr=1;mem_rd=0;#5// writes
		mem_rd=1;mem_wr=0;#5//reads


		$finish;

	end
      
endmodule

data_memory/data_memory.vcd
$date
	Sun May 14 14:22:46 2023
$end
$version
	Icarus Verilog
$end
$timescale
	1ps
$end
$scope module data_memory_tb $end
$var wire 32 ! read_data [31:0] $end
$var reg 32 " address [31:0] $end
$var reg 1 # clk $end
$var reg 1 $ mem_rd $end
$var reg 1 % mem_wr $end
$var reg 1 & size $end
$var reg 32 ' write_data [31:0] $end
$scope module uut $end
$var wire 32 ( address [31:0] $end
$var wire 1 ) clk $end
$var wire 1 * mem_rd $end
$var wire 1 + mem_wr $end
$var wire 1 , size $end
$var wire 32 - write_data [31:0] $end
$var reg 32 . read_data [31:0] $end
$upscope $end
$upscope $end
$enddefinitions $end
#0
$dumpvars
bx .
b100010101 -
0,
1+
0*
1)
b0 (
b100010101 '
0&
1%
0$
1#
b0 "
bx !
$end
#1000
0#
0)
#2000
1#
1)
#3000
0#
0)
#4000
1#
1)
#5000
0#
0)
0%
0+
1$
1*
#6000
b10101 .
b10101 !
1#
1)
#7000
0#
0)
#8000
1#
1)
#9000
0#
0)
#10000
bx00010101 .
bx00010101 !
1#
1)
0$
0*
1%
1+
1&
1,
b100010101 "
b100010101 (
#11000
0#
0)
#12000
b100010101 .
b100010101 !
1#
1)
#13000
0#
0)
#14000
b100010101 .
1#
1)
#15000
0#
0)
0%
0+
1$
1*
#16000
b100010101 .
1#
1)
#17000
0#
0)
#18000
b100010101 .
1#
1)
#19000
0#
0)
#20000
b100010101 .
1#
1)
