data_memory/data_memory.v
`timescale 1ns / 1ps

module data_memory(read_data,clk,address,write_data,mem_rd,mem_wr);
input clk;
input [31:0] address;
input [31:0] write_data;
input mem_rd;
input mem_wr;

reg [31:0] memory[256:0];// 1023 locations of 4 bytes == 1024 bytes totals.
output reg [31:0] read_data;

always@(posedge clk)begin
	
	if(mem_rd==1)
		read_data=memory[address];
	if(mem_wr==1)
		memory[address]=write_data;

end

endmodule

data_memory/data_memory_tb.v
`timescale 1ns / 1ps
`include"data_memory.v"

module data_memory_tb;

	// Inputs
	reg clk;
	reg [31:0] address;
	reg [31:0] write_data;
	reg mem_rd;
	reg mem_wr;

	// Outputs
	wire [31:0] read_data;

	// Instantiate the Unit Under Test (UUT)
	data_memory uut (
		.read_data(read_data), 
		.clk(clk), 
		.address(address), 
		.write_data(write_data), 
		.mem_rd(mem_rd), 
		.mem_wr(mem_wr)
	);
always#1clk=~clk;
	initial begin
		// Initialize Inputs
        $dumpfile("data_memory.vcd");
        $dumpvars(0,data_memory_tb);

		clk = 1;
		address = 0;
		write_data = 0;
		mem_rd = 0;
		mem_wr = 0;

		repeat(32)begin
			write_data=address+1;
			mem_wr=1;mem_rd=0;#5// writes
			mem_rd=1;mem_wr=0;#5//reads
			address=address+1;
		end

		$finish;

	end
      
endmodule

data_memory/data_memory.vcd
$date
	Sat May 13 17:53:28 2023
$end
$version
	Icarus Verilog
$end
$timescale
	1ps
$end
$scope module data_memory_tb $end
$var wire 32 ! read_data [31:0] $end
$var reg 32 " address [31:0] $end
$var reg 1 # clk $end
$var reg 1 $ mem_rd $end
$var reg 1 % mem_wr $end
$var reg 32 & write_data [31:0] $end
$scope module uut $end
$var wire 32 ' address [31:0] $end
$var wire 1 ( clk $end
$var wire 1 ) mem_rd $end
$var wire 1 * mem_wr $end
$var wire 32 + write_data [31:0] $end
$var reg 32 , read_data [31:0] $end
$upscope $end
$upscope $end
$enddefinitions $end
#0
$dumpvars
bx ,
b1 +
1*
0)
1(
b0 '
b1 &
1%
0$
1#
b0 "
bx !
$end
#1000
0#
0(
#2000
1#
1(
#3000
0#
0(
#4000
1#
1(
#5000
0#
0(
0%
0*
1$
1)
#6000
b1 ,
b1 !
1#
1(
#7000
0#
0(
#8000
1#
1(
#9000
0#
0(
#10000
1#
1(
0$
0)
1%
1*
b10 &
b10 +
b1 "
b1 '
#11000
0#
0(
#12000
1#
1(
#13000
0#
0(
#14000
1#
1(
#15000
0#
0(
0%
0*
1$
1)
#16000
b10 ,
b10 !
1#
1(
#17000
0#
0(
#18000
1#
1(
#19000
0#
0(
#20000
1#
1(
0$
0)
1%
1*
b11 &
b11 +
b10 "
b10 '
#21000
0#
0(
#22000
1#
1(
#23000
0#
0(
#24000
1#
1(
#25000
0#
0(
0%
0*
1$
1)
#26000
b11 ,
b11 !
1#
1(
#27000
0#
0(
#28000
1#
1(
#29000
0#
0(
#30000
1#
1(
0$
0)
1%
1*
b100 &
b100 +
b11 "
b11 '
#31000
0#
0(
#32000
1#
1(
#33000
0#
0(
#34000
1#
1(
#35000
0#
0(
0%
0*
1$
1)
#36000
b100 ,
b100 !
1#
1(
#37000
0#
0(
#38000
1#
1(
#39000
0#
0(
#40000
1#
1(
0$
0)
1%
1*
b101 &
b101 +
b100 "
b100 '
#41000
0#
0(
#42000
1#
1(
#43000
0#
0(
#44000
1#
1(
#45000
0#
0(
0%
0*
1$
1)
#46000
b101 ,
b101 !
1#
1(
#47000
0#
0(
#48000
1#
1(
#49000
0#
0(
#50000
1#
1(
0$
0)
1%
1*
b110 &
b110 +
b101 "
b101 '
#51000
0#
0(
#52000
1#
1(
#53000
0#
0(
#54000
1#
1(
#55000
0#
0(
0%
0*
1$
1)
#56000
b110 ,
b110 !
1#
1(
#57000
0#
0(
#58000
1#
1(
#59000
0#
0(
#60000
1#
1(
0$
0)
1%
1*
b111 &
b111 +
b110 "
b110 '
#61000
0#
0(
#62000
1#
1(
#63000
0#
0(
#64000
1#
1(
#65000
0#
0(
0%
0*
1$
1)
#66000
b111 ,
b111 !
1#
1(
#67000
0#
0(
#68000
1#
1(
#69000
0#
0(
#70000
1#
1(
0$
0)
1%
1*
b1000 &
b1000 +
b111 "
b111 '
#71000
0#
0(
#72000
1#
1(
#73000
0#
0(
#74000
1#
1(
#75000
0#
0(
0%
0*
1$
1)
#76000
b1000 ,
b1000 !
1#
1(
#77000
0#
0(
#78000
1#
1(
#79000
0#
0(
#80000
1#
1(
0$
0)
1%
1*
b1001 &
b1001 +
b1000 "
b1000 '
#81000
0#
0(
#82000
1#
1(
#83000
0#
0(
#84000
1#
1(
#85000
0#
0(
0%
0*
1$
1)
#86000
b1001 ,
b1001 !
1#
1(
#87000
0#
0(
#88000
1#
1(
#89000
0#
0(
#90000
1#
1(
0$
0)
1%
1*
b1010 &
b1010 +
b1001 "
b1001 '
#91000
0#
0(
#92000
1#
1(
#93000
0#
0(
#94000
1#
1(
#95000
0#
0(
0%
0*
1$
1)
#96000
b1010 ,
b1010 !
1#
1(
#97000
0#
0(
#98000
1#
1(
#99000
0#
0(
#100000
1#
1(
0$
0)
1%
1*
b1011 &
b1011 +
b1010 "
b1010 '
#101000
0#
0(
#102000
1#
1(
#103000
0#
0(
#104000
1#
1(
#105000
0#
0(
0%
0*
1$
1)
#106000
b1011 ,
b1011 !
1#
1(
#107000
0#
0(
#108000
1#
1(
#109000
0#
0(
#110000
1#
1(
0$
0)
1%
1*
b1100 &
b1100 +
b1011 "
b1011 '
#111000
0#
0(
#112000
1#
1(
#113000
0#
0(
#114000
1#
1(
#115000
0#
0(
0%
0*
1$
1)
#116000
b1100 ,
b1100 !
1#
1(
#117000
0#
0(
#118000
1#
1(
#119000
0#
0(
#120000
1#
1(
0$
0)
1%
1*
b1101 &
b1101 +
b1100 "
b1100 '
#121000
0#
0(
#122000
1#
1(
#123000
0#
0(
#124000
1#
1(
#125000
0#
0(
0%
0*
1$
1)
#126000
b1101 ,
b1101 !
1#
1(
#127000
0#
0(
#128000
1#
1(
#129000
0#
0(
#130000
1#
1(
0$
0)
1%
1*
b1110 &
b1110 +
b1101 "
b1101 '
#131000
0#
0(
#132000
1#
1(
#133000
0#
0(
#134000
1#
1(
#135000
0#
0(
0%
0*
1$
1)
#136000
b1110 ,
b1110 !
1#
1(
#137000
0#
0(
#138000
1#
1(
#139000
0#
0(
#140000
1#
1(
0$
0)
1%
1*
b1111 &
b1111 +
b1110 "
b1110 '
#141000
0#
0(
#142000
1#
1(
#143000
0#
0(
#144000
1#
1(
#145000
0#
0(
0%
0*
1$
1)
#146000
b1111 ,
b1111 !
1#
1(
#147000
0#
0(
#148000
1#
1(
#149000
0#
0(
#150000
1#
1(
0$
0)
1%
1*
b10000 &
b10000 +
b1111 "
b1111 '
#151000
0#
0(
#152000
1#
1(
#153000
0#
0(
#154000
1#
1(
#155000
0#
0(
0%
0*
1$
1)
#156000
b10000 ,
b10000 !
1#
1(
#157000
0#
0(
#158000
1#
1(
#159000
0#
0(
#160000
1#
1(
0$
0)
1%
1*
b10001 &
b10001 +
b10000 "
b10000 '
#161000
0#
0(
#162000
1#
1(
#163000
0#
0(
#164000
1#
1(
#165000
0#
0(
0%
0*
1$
1)
#166000
b10001 ,
b10001 !
1#
1(
#167000
0#
0(
#168000
1#
1(
#169000
0#
0(
#170000
1#
1(
0$
0)
1%
1*
b10010 &
b10010 +
b10001 "
b10001 '
#171000
0#
0(
#172000
1#
1(
#173000
0#
0(
#174000
1#
1(
#175000
0#
0(
0%
0*
1$
1)
#176000
b10010 ,
b10010 !
1#
1(
#177000
0#
0(
#178000
1#
1(
#179000
0#
0(
#180000
1#
1(
0$
0)
1%
1*
b10011 &
b10011 +
b10010 "
b10010 '
#181000
0#
0(
#182000
1#
1(
#183000
0#
0(
#184000
1#
1(
#185000
0#
0(
0%
0*
1$
1)
#186000
b10011 ,
b10011 !
1#
1(
#187000
0#
0(
#188000
1#
1(
#189000
0#
0(
#190000
1#
1(
0$
0)
1%
1*
b10100 &
b10100 +
b10011 "
b10011 '
#191000
0#
0(
#192000
1#
1(
#193000
0#
0(
#194000
1#
1(
#195000
0#
0(
0%
0*
1$
1)
#196000
b10100 ,
b10100 !
1#
1(
#197000
0#
0(
#198000
1#
1(
#199000
0#
0(
#200000
1#
1(
0$
0)
1%
1*
b10101 &
b10101 +
b10100 "
b10100 '
#201000
0#
0(
#202000
1#
1(
#203000
0#
0(
#204000
1#
1(
#205000
0#
0(
0%
0*
1$
1)
#206000
b10101 ,
b10101 !
1#
1(
#207000
0#
0(
#208000
1#
1(
#209000
0#
0(
#210000
1#
1(
0$
0)
1%
1*
b10110 &
b10110 +
b10101 "
b10101 '
#211000
0#
0(
#212000
1#
1(
#213000
0#
0(
#214000
1#
1(
#215000
0#
0(
0%
0*
1$
1)
#216000
b10110 ,
b10110 !
1#
1(
#217000
0#
0(
#218000
1#
1(
#219000
0#
0(
#220000
1#
1(
0$
0)
1%
1*
b10111 &
b10111 +
b10110 "
b10110 '
#221000
0#
0(
#222000
1#
1(
#223000
0#
0(
#224000
1#
1(
#225000
0#
0(
0%
0*
1$
1)
#226000
b10111 ,
b10111 !
1#
1(
#227000
0#
0(
#228000
1#
1(
#229000
0#
0(
#230000
1#
1(
0$
0)
1%
1*
b11000 &
b11000 +
b10111 "
b10111 '
#231000
0#
0(
#232000
1#
1(
#233000
0#
0(
#234000
1#
1(
#235000
0#
0(
0%
0*
1$
1)
#236000
b11000 ,
b11000 !
1#
1(
#237000
0#
0(
#238000
1#
1(
#239000
0#
0(
#240000
1#
1(
0$
0)
1%
1*
b11001 &
b11001 +
b11000 "
b11000 '
#241000
0#
0(
#242000
1#
1(
#243000
0#
0(
#244000
1#
1(
#245000
0#
0(
0%
0*
1$
1)
#246000
b11001 ,
b11001 !
1#
1(
#247000
0#
0(
#248000
1#
1(
#249000
0#
0(
#250000
1#
1(
0$
0)
1%
1*
b11010 &
b11010 +
b11001 "
b11001 '
#251000
0#
0(
#252000
1#
1(
#253000
0#
0(
#254000
1#
1(
#255000
0#
0(
0%
0*
1$
1)
#256000
b11010 ,
b11010 !
1#
1(
#257000
0#
0(
#258000
1#
1(
#259000
0#
0(
#260000
1#
1(
0$
0)
1%
1*
b11011 &
b11011 +
b11010 "
b11010 '
#261000
0#
0(
#262000
1#
1(
#263000
0#
0(
#264000
1#
1(
#265000
0#
0(
0%
0*
1$
1)
#266000
b11011 ,
b11011 !
1#
1(
#267000
0#
0(
#268000
1#
1(
#269000
0#
0(
#270000
1#
1(
0$
0)
1%
1*
b11100 &
b11100 +
b11011 "
b11011 '
#271000
0#
0(
#272000
1#
1(
#273000
0#
0(
#274000
1#
1(
#275000
0#
0(
0%
0*
1$
1)
#276000
b11100 ,
b11100 !
1#
1(
#277000
0#
0(
#278000
1#
1(
#279000
0#
0(
#280000
1#
1(
0$
0)
1%
1*
b11101 &
b11101 +
b11100 "
b11100 '
#281000
0#
0(
#282000
1#
1(
#283000
0#
0(
#284000
1#
1(
#285000
0#
0(
0%
0*
1$
1)
#286000
b11101 ,
b11101 !
1#
1(
#287000
0#
0(
#288000
1#
1(
#289000
0#
0(
#290000
1#
1(
0$
0)
1%
1*
b11110 &
b11110 +
b11101 "
b11101 '
#291000
0#
0(
#292000
1#
1(
#293000
0#
0(
#294000
1#
1(
#295000
0#
0(
0%
0*
1$
1)
#296000
b11110 ,
b11110 !
1#
1(
#297000
0#
0(
#298000
1#
1(
#299000
0#
0(
#300000
1#
1(
0$
0)
1%
1*
b11111 &
b11111 +
b11110 "
b11110 '
#301000
0#
0(
#302000
1#
1(
#303000
0#
0(
#304000
1#
1(
#305000
0#
0(
0%
0*
1$
1)
#306000
b11111 ,
b11111 !
1#
1(
#307000
0#
0(
#308000
1#
1(
#309000
0#
0(
#310000
1#
1(
0$
0)
1%
1*
b100000 &
b100000 +
b11111 "
b11111 '
#311000
0#
0(
#312000
1#
1(
#313000
0#
0(
#314000
1#
1(
#315000
0#
0(
0%
0*
1$
1)
#316000
b100000 ,
b100000 !
1#
1(
#317000
0#
0(
#318000
1#
1(
#319000
0#
0(
#320000
bx ,
bx !
1#
1(
b100000 "
b100000 '
