Decoder/decoder.v
`timescale 1ns / 1ps

module decoder(clk,instruction,func3,func7,opcode,r1,r2,rd,imm);

input clk;
input [31:0] instruction;// instruction 32 bit
output reg [2:0] func3;//func3 part
output reg [6:0] func7;// func7 part
output reg [6:0] opcode;//opcode part
output reg [4:0] r1,r2,rd;// address of r1,r2,rd
output reg [20:0] imm;//maximum imm can be 20 

parameter r_type=7'b0110011;// add sub etc
parameter s_type=7'b0100011;//sw sb
parameter i_type=7'b0010011;// addi
parameter l_type=7'b0000011;//lw lb
parameter b_type=7'b1100011;//beq bge blt
parameter jal_type=7'b1101111;// jal
parameter jalr_type=7'b1100111;//jalr

always @(posedge clk) begin
    
    opcode=instruction[6:0];

    case (opcode)
    r_type:
    begin
        rd=instruction[11:7];
        func3=instruction[14:12];
        r1=instruction[19:15];
        r2=instruction[24:20];
        func7=instruction[31:25];
    end
    s_type:
        begin
            imm[4:0]=instruction[11:7];
            func3=instruction[14:12];
            r1=instruction[19:15];
            r2=instruction[24:20];
            imm[11:5]=instruction[31:25];
        end
    i_type:
    begin
        rd=instruction[11:7];
        func3=instruction[14:12];
        r1=instruction[19:15];
        func7=7'bx;
        imm[11:0]=instruction[31:20];
    end
    l_type:
    begin
        rd=instruction[11:7];
        func3=instruction[14:12];
        r1=instruction[19:15];
        func7=7'bx;
        imm[11:0]=instruction[31:20];
    end
    b_type:// shifted right once
    begin
        
        imm[11]=instruction[7];
        imm[4:1]=instruction[11:8];
        func3=instruction[14:12];
        r1=instruction[19:15];
        r2=instruction[24:20];
        imm[10:5]=instruction[30:25];
        imm[12]=instruction[31];

        imm=imm>>>1;//signed right shift
        rd=5'bx;
        func7=7'bx;
    end
    jal_type:begin
        
        rd=instruction[11:7];
        imm[19:12]=instruction[19:12];
        imm[11]=instruction[20];
        imm[10:1]=instruction[30:21];
        imm[20]=instruction[31];

        imm=imm>>>1;//signed right shift
        func3=3'bx;
        r1=5'bx;
        r2=5'bx;
        func7=7'bx;
    end
    jalr_type:
    begin
        rd=instruction[11:7];
        func3=instruction[14:12];
        r1=instruction[19:15];
        func7=7'bx;
        imm[11:0]=instruction[31:20];
    end
    endcase
end
    
endmodule

Decoder/decoder_tb.v
`timescale 1ns / 1ps
`include "decoder.v"

module decoder_tb;

reg clk;
reg [31:0] instruction;// instruction 32 bit
wire [2:0] func3;//func3 part
wire [6:0] func7;// func7 part
wire [6:0] opcode;//opcode part
wire [4:0] r1,r2,rd;// address of r1,r2,rd
wire [20:0] imm;//maximum imm can be 20 

decoder uut(clk,instruction,func3,func7,opcode,r1,r2,rd,imm);
    
always#1clk=~clk;
initial begin
    $dumpfile("decoder.vcd");
    $dumpvars(0,decoder_tb);

    clk=0;#2;
        instruction = 32'b00000000001000001000000010110011;#10 // add x1 x1 x2
        instruction = 32'b00000000001000001000000011100011;#10 // beq x1 x2 2048
        instruction = 32'b00000000000010000000000011101111;#10 // jal x1 2048
    $finish;
end 
endmodule

Decoder/decoder.vcd
$date
	Sun May 14 02:14:04 2023
$end
$version
	Icarus Verilog
$end
$timescale
	1ps
$end
$scope module decoder_tb $end
$var wire 3 ! func3 [2:0] $end
$var wire 7 " func7 [6:0] $end
$var wire 21 # imm [20:0] $end
$var wire 7 $ opcode [6:0] $end
$var wire 5 % r1 [4:0] $end
$var wire 5 & r2 [4:0] $end
$var wire 5 ' rd [4:0] $end
$var reg 1 ( clk $end
$var reg 32 ) instruction [31:0] $end
$scope module uut $end
$var wire 1 * clk $end
$var wire 32 + instruction [31:0] $end
$var reg 3 , func3 [2:0] $end
$var reg 7 - func7 [6:0] $end
$var reg 21 . imm [20:0] $end
$var reg 7 / opcode [6:0] $end
$var reg 5 0 r1 [4:0] $end
$var reg 5 1 r2 [4:0] $end
$var reg 5 2 rd [4:0] $end
$upscope $end
$upscope $end
$enddefinitions $end
#0
$dumpvars
bx 2
bx 1
bx 0
bx /
bx .
bx -
bx ,
bx +
0*
bx )
0(
bx '
bx &
bx %
bx $
bx #
bx "
bx !
$end
#1000
1(
1*
#2000
0(
0*
b1000001000000010110011 )
b1000001000000010110011 +
#3000
b0 -
b0 "
b10 1
b10 &
b1 0
b1 %
b0 ,
b0 !
b1 2
b1 '
b110011 /
b110011 $
1(
1*
#4000
0(
0*
#5000
1(
1*
#6000
0(
0*
#7000
1(
1*
#8000
0(
0*
#9000
1(
1*
#10000
0(
0*
#11000
1(
1*
#12000
0(
0*
b1000001000000011100011 )
b1000001000000011100011 +
#13000
bx -
bx "
bx 2
bx '
b0xxxxxxxx010000000000 .
b0xxxxxxxx010000000000 #
b1100011 /
b1100011 $
1(
1*
#14000
0(
0*
#15000
b0xxxxxxx010000000000 .
b0xxxxxxx010000000000 #
1(
1*
#16000
0(
0*
#17000
b0xxxxxx010000000000 .
b0xxxxxx010000000000 #
1(
1*
#18000
0(
0*
#19000
b0xxxxx010000000000 .
b0xxxxx010000000000 #
1(
1*
#20000
0(
0*
#21000
b0xxxx010000000000 .
b0xxxx010000000000 #
1(
1*
#22000
0(
0*
b10000000000011101111 )
b10000000000011101111 +
#23000
bx 1
bx &
bx 0
bx %
bx ,
bx !
b1000000000000000000 .
b1000000000000000000 #
b1 2
b1 '
b1101111 /
b1101111 $
1(
1*
#24000
0(
0*
#25000
b1000000000000000000 .
b1000000000000000000 #
1(
1*
#26000
0(
0*
#27000
b1000000000000000000 .
b1000000000000000000 #
1(
1*
#28000
0(
0*
#29000
b1000000000000000000 .
b1000000000000000000 #
1(
1*
#30000
0(
0*
#31000
b1000000000000000000 .
b1000000000000000000 #
1(
1*
