ALU/alu.v
`timescale 1ns / 1ps


module alu(clk,a,b,out,alu_control,zero_flag);//s is ALU CONTROL
input clk;
input [31:0] a,b;
input [2:0] alu_control;
output reg zero_flag;
output reg [31:0] out;

always@(posedge clk)
begin
	case(alu_control)
	3'b000:
		out=a&b;
	3'b001:
		out=a|b;	
	3'b010:
		out=a+b;
	3'b011:
		out=a-b;
	3'b100:
    begin
        if(a<b)
            out=0;
        else 
            out=1; 
    end
	3'b101:
	 begin
        if(a>=b)
            out=0;
        else 
            out=1; 
    end
	3'b110:
	 begin
        if(a==b)
            out=0;
        else 
            out=1; 
    end
	endcase

    if(out==0)
        zero_flag=1;
    else
        zero_flag=0;
end 
endmodule

ALU/alu_tb.v
`timescale 1ns / 1ps
`include "alu.v"

module alu_tb;

    reg clk;
    reg [31:0] a,b;
    
    reg [2:0] alu_control;

    wire zero_flag;
    wire [31:0] out;

    alu uut(clk,a,b,out,alu_control,zero_flag);

always#1clk=~clk;
initial begin
    $dumpfile("alu.vcd");
    $dumpvars(0,alu_tb);

    clk=0;a=3;b=2;#2;

    alu_control=3'b000;#2;// and
    alu_control=3'b001;#2;//or 
    alu_control=3'b010;#2;// add
    alu_control=3'b011;#2;// sub
    alu_control=3'b100;#2;// less then
    alu_control=3'b101;#2;//greter then or equal to
    alu_control=3'b110;#2;//equal to
    $finish;

end

    
endmodule

ALU/alu.vcd
$date
	Sat May 13 19:00:55 2023
$end
$version
	Icarus Verilog
$end
$timescale
	1ps
$end
$scope module alu_tb $end
$var wire 32 ! out [31:0] $end
$var wire 1 " zero_flag $end
$var reg 32 # a [31:0] $end
$var reg 3 $ alu_control [2:0] $end
$var reg 32 % b [31:0] $end
$var reg 1 & clk $end
$scope module uut $end
$var wire 32 ' a [31:0] $end
$var wire 3 ( alu_control [2:0] $end
$var wire 32 ) b [31:0] $end
$var wire 1 * clk $end
$var reg 32 + out [31:0] $end
$var reg 1 , zero_flag $end
$upscope $end
$upscope $end
$enddefinitions $end
#0
$dumpvars
x,
bx +
0*
b10 )
bx (
b11 '
0&
b10 %
bx $
b11 #
x"
bx !
$end
#1000
0,
0"
1&
1*
#2000
0&
0*
b0 $
b0 (
#3000
b10 +
b10 !
1&
1*
#4000
0&
0*
b1 $
b1 (
#5000
b11 +
b11 !
1&
1*
#6000
0&
0*
b10 $
b10 (
#7000
b101 +
b101 !
1&
1*
#8000
0&
0*
b11 $
b11 (
#9000
b1 +
b1 !
1&
1*
#10000
0&
0*
b100 $
b100 (
#11000
1&
1*
#12000
0&
0*
b101 $
b101 (
#13000
1,
1"
b0 +
b0 !
1&
1*
#14000
0&
0*
b110 $
b110 (
#15000
0,
0"
b1 +
b1 !
1&
1*
