ProgramCounter/ProgramCounter.v
`timescale 1ns / 1ps
//////////////////////////////////////////////////////////////////////////////////
// Company: 
// Engineer: 
// 
// Create Date:    12:32:37 04/10/2023 
// Design Name: 
// Module Name:    ProgramCounter 
// Project Name: 
// Target Devices: 
// Tool versions: 
// Description: 
//
// Dependencies: 
//
// Revision: 
// Revision 0.01 - File Created
// Additional Comments: 
//
//////////////////////////////////////////////////////////////////////////////////
module ProgramCounter(
input clk,reset,
input [19:0]offset,
input branch,
output reg [15:0] count
);


always@(posedge clk)begin
	if(reset)
		count=0;
	if(branch)
		count=count+offset;
	else
		count=count+4;

end

endmodule

ProgramCounter/PC_TB.v
`timescale 1ns / 1ps
`include "ProgramCounter.v"

////////////////////////////////////////////////////////////////////////////////
// Company: 
// Engineer:
//
// Create Date:   12:36:17 04/10/2023
// Design Name:   ProgramCounter
// Module Name:   C:/Users/DSA Lab/Desktop/2021234/Lab_9/PC_TB.v
// Project Name:  Lab_9
// Target Device:  
// Tool versions:  
// Description: 
//
// Verilog Test Fixture created by ISE for module: ProgramCounter
//
// Dependencies:
// 
// Revision:
// Revision 0.01 - File Created
// Additional Comments:
// 
////////////////////////////////////////////////////////////////////////////////

module PC_TB;

	// Inputs
	reg clk;
	reg reset;
	reg [19:0] offset;
	reg branch;

	// Outputs
	wire [15:0] count;

	// Instantiate the Unit Under Test (UUT)
	ProgramCounter uut (
		.clk(clk), 
		.reset(reset), 
		.offset(offset),
		.branch(branch),
		.count(count)
		
	);
always#1clk=~clk;
	initial begin

		$dumpfile("ProgramCounter.vcd");
        $dumpvars(0,PC_TB);
		// Initialize Inputs
		clk = 0;reset = 1;branch=0;offset=0;
		
		#2;
		reset=0;
		offset=24;
		branch=1;
		#5;
		branch=0;offset=0;
		#5
		reset=0;
		#2;
		

		// Wait 100 ns for global reset to finish
	$finish;        
		// Add stimulus here

	end
      
endmodule

ProgramCounter/ProgramCounter.vcd
$date
	Sat May 13 16:02:14 2023
$end
$version
	Icarus Verilog
$end
$timescale
	1ps
$end
$scope module PC_TB $end
$var wire 16 ! count [15:0] $end
$var reg 1 " branch $end
$var reg 1 # clk $end
$var reg 20 $ offset [19:0] $end
$var reg 1 % reset $end
$scope module uut $end
$var wire 1 & branch $end
$var wire 1 ' clk $end
$var wire 20 ( offset [19:0] $end
$var wire 1 ) reset $end
$var reg 16 * count [15:0] $end
$upscope $end
$upscope $end
$enddefinitions $end
#0
$dumpvars
bx *
1)
b0 (
0'
0&
1%
b0 $
0#
0"
bx !
$end
#1000
b100 *
b100 !
1#
1'
#2000
0#
0'
1"
1&
b11000 $
b11000 (
0%
0)
#3000
b11100 *
b11100 !
1#
1'
#4000
0#
0'
#5000
b110100 *
b110100 !
1#
1'
#6000
0#
0'
#7000
b111000 *
b111000 !
1#
1'
b0 $
b0 (
0"
0&
#8000
0#
0'
#9000
b111100 *
b111100 !
1#
1'
#10000
0#
0'
#11000
b1000000 *
b1000000 !
1#
1'
#12000
0#
0'
#13000
b1000100 *
b1000100 !
1#
1'
